<?xml version="1.0" encoding="UTF-8"?>
<beans xmlns="http://www.springframework.org/schema/beans" xmlns:xsi="http://www.w3.org/2001/XMLSchema-instance"
  xmlns:aop="http://www.springframework.org/schema/aop"
  xsi:schemaLocation="http://www.springframework.org/schema/beans http://www.springframework.org/schema/beans/spring-beans-4.3.xsd
    http://www.springframework.org/schema/aop http://www.springframework.org/schema/aop/spring-aop-4.3.xsd">

  <bean id="org.hisp.dhis.preheat.PreheatService" class="org.hisp.dhis.preheat.DefaultPreheatService" scope="prototype">
    <aop:scoped-proxy proxy-target-class="false" />
  </bean>

  <bean id="org.hisp.dhis.calendar.CalendarService" class="org.hisp.dhis.calendar.DefaultCalendarService" />

  <bean class="org.hisp.dhis.calendar.impl.Iso8601Calendar" />

  <bean class="org.hisp.dhis.calendar.impl.CopticCalendar" />

  <bean class="org.hisp.dhis.calendar.impl.EthiopianCalendar" />

  <bean class="org.hisp.dhis.calendar.impl.GregorianCalendar" />

  <bean class="org.hisp.dhis.calendar.impl.IslamicCalendar" />

  <bean class="org.hisp.dhis.calendar.impl.NepaliCalendar" />

  <bean class="org.hisp.dhis.calendar.impl.ThaiCalendar" />

  <bean class="org.hisp.dhis.calendar.impl.PersianCalendar" />

  <bean id="org.hisp.dhis.query.planner.QueryPlanner" class="org.hisp.dhis.query.planner.DefaultQueryPlanner" />

  <bean id="org.hisp.dhis.query.QueryParser" class="org.hisp.dhis.query.DefaultQueryParser" />

  <bean id="org.hisp.dhis.query.CriteriaQueryEngine" class="org.hisp.dhis.query.CriteriaQueryEngine" />

  <bean id="org.hisp.dhis.query.InMemoryQueryEngine" class="org.hisp.dhis.query.InMemoryQueryEngine" />

  <bean id="org.hisp.dhis.query.QueryService" class="org.hisp.dhis.query.DefaultQueryService" />

  <bean class="org.hisp.dhis.patch.DefaultPatchService" />

  <bean id="org.hisp.dhis.render.RenderService" class="org.hisp.dhis.render.DefaultRenderService" />

  <bean class="org.hisp.dhis.amqp.RabbitMQAmqpService" />

  <!-- Store definitions -->

  <bean id="org.hisp.dhis.report.ReportStore" class="org.hisp.dhis.common.hibernate.HibernateIdentifiableObjectStore">
    <property name="clazz" value="org.hisp.dhis.report.Report" />
    <property name="sessionFactory" ref="sessionFactory" />
    <property name="cacheable" value="true" />
  </bean>

  <bean id="org.hisp.dhis.chart.ChartStore" class="org.hisp.dhis.common.hibernate.HibernateAnalyticalObjectStore">
    <property name="clazz" value="org.hisp.dhis.chart.Chart" />
    <property name="sessionFactory" ref="sessionFactory" />
    <property name="cacheable" value="true" />
  </bean>

  <bean id="org.hisp.dhis.reporttable.ReportTableStore" class="org.hisp.dhis.common.hibernate.HibernateAnalyticalObjectStore">
    <property name="clazz" value="org.hisp.dhis.reporttable.ReportTable" />
    <property name="sessionFactory" ref="sessionFactory" />
    <property name="cacheable" value="true" />
  </bean>

  <bean id="org.hisp.dhis.dashboard.DashboardStore" class="org.hisp.dhis.common.hibernate.HibernateIdentifiableObjectStore">
    <property name="clazz" value="org.hisp.dhis.dashboard.Dashboard" />
    <property name="sessionFactory" ref="sessionFactory" />
    <property name="cacheable" value="true" />
  </bean>

  <bean id="org.hisp.dhis.dashboard.DashboardItemStore" class="org.hisp.dhis.dashboard.hibernate.HibernateDashboardItemStore">
    <property name="clazz" value="org.hisp.dhis.dashboard.DashboardItem" />
    <property name="sessionFactory" ref="sessionFactory" />
    <property name="cacheable" value="true" />
  </bean>

  <bean id="org.hisp.dhis.interpretation.InterpretationStore" class="org.hisp.dhis.interpretation.hibernate.HibernateInterpretationStore">
    <property name="clazz" value="org.hisp.dhis.interpretation.Interpretation" />
    <property name="sessionFactory" ref="sessionFactory" />
  </bean>

  <bean id="org.hisp.dhis.dataentryform.DataEntryFormStore" class="org.hisp.dhis.dataentryform.hibernate.HibernateDataEntryFormStore">
    <property name="clazz" value="org.hisp.dhis.dataentryform.DataEntryForm" />
    <property name="sessionFactory" ref="sessionFactory" />
    <property name="cacheable" value="true" />
  </bean>

  <bean id="org.hisp.dhis.dataelement.DataElementStore" class="org.hisp.dhis.dataelement.hibernate.HibernateDataElementStore">
    <property name="clazz" value="org.hisp.dhis.dataelement.DataElement" />
    <property name="sessionFactory" ref="sessionFactory" />
    <property name="jdbcTemplate" ref="jdbcTemplate" />
    <property name="cacheable" value="true" />
  </bean>

  <bean id="org.hisp.dhis.dataelement.DataElementOperandStore" class="org.hisp.dhis.dataelement.hibernate.HibernateDataElementOperandStore">
    <property name="clazz" value="org.hisp.dhis.dataelement.DataElementOperand" />
    <property name="sessionFactory" ref="sessionFactory" />
    <property name="jdbcTemplate" ref="jdbcTemplate" />
    <property name="cacheable" value="true" />
    <property name="transientIdentifiableProperties" value="true" />
  </bean>

  <bean id="org.hisp.dhis.dataelement.DataElementGroupStore" class="org.hisp.dhis.dataelement.hibernate.HibernateDataElementGroupStore">
    <property name="clazz" value="org.hisp.dhis.dataelement.DataElementGroup" />
    <property name="sessionFactory" ref="sessionFactory" />
    <property name="cacheable" value="true" />
  </bean>

  <bean id="org.hisp.dhis.dataelement.DataElementGroupSetStore"
    class="org.hisp.dhis.dataelement.hibernate.HibernateDataElementGroupSetStore">
    <property name="clazz" value="org.hisp.dhis.dataelement.DataElementGroupSet" />
    <property name="sessionFactory" ref="sessionFactory" />
    <property name="cacheable" value="true" />
  </bean>

  <bean id="org.hisp.dhis.datavalue.DataValueStore" class="org.hisp.dhis.datavalue.hibernate.HibernateDataValueStore">
    <property name="clazz" value="org.hisp.dhis.datavalue.DataValue" />
    <property name="sessionFactory" ref="sessionFactory" />
    <property name="periodStore" ref="org.hisp.dhis.period.PeriodStore" />
    <property name="jdbcTemplate" ref="jdbcTemplate" />
    <property name="statementBuilder" ref="statementBuilder" />
  </bean>

  <bean id="org.hisp.dhis.datavalue.DataAccessManager" class="org.hisp.dhis.datavalue.DefaultAggregateAccessManager" />

  <bean id="org.hisp.dhis.dataapproval.DataApprovalStore" class="org.hisp.dhis.dataapproval.hibernate.HibernateDataApprovalStore">
    <property name="clazz" value="org.hisp.dhis.dataapproval.DataApproval" />
    <property name="jdbcTemplate" ref="jdbcTemplate" />
    <property name="sessionFactory" ref="sessionFactory" />
    <property name="periodService" ref="org.hisp.dhis.period.PeriodService" />
    <property name="currentUserService" ref="org.hisp.dhis.user.CurrentUserService" />
    <property name="categoryService" ref="org.hisp.dhis.category.CategoryService" />
    <property name="dataApprovalLevelService" ref="org.hisp.dhis.dataapproval.DataApprovalLevelService" />
    <property name="systemSettingManager" ref="org.hisp.dhis.setting.SystemSettingManager" />
  </bean>

  <bean id="org.hisp.dhis.dataapproval.DataApprovalAuditStore" class="org.hisp.dhis.dataapproval.hibernate.HibernateDataApprovalAuditStore">
    <property name="clazz" value="org.hisp.dhis.dataapproval.DataApprovalAudit" />
    <property name="sessionFactory" ref="sessionFactory" />
    <property name="cacheable" value="true" />
    <property name="currentUserService" ref="org.hisp.dhis.user.CurrentUserService" />
  </bean>

  <bean id="org.hisp.dhis.dataapproval.DataApprovalLevelStore" class="org.hisp.dhis.dataapproval.hibernate.HibernateDataApprovalLevelStore">
    <property name="clazz" value="org.hisp.dhis.dataapproval.DataApprovalLevel" />
    <property name="sessionFactory" ref="sessionFactory" />
    <property name="cacheable" value="true" />
  </bean>

  <bean id="org.hisp.dhis.dataapproval.DataApprovalWorkflowStore"
    class="org.hisp.dhis.dataapproval.hibernate.HibernateDataApprovalWorkflowStore">
    <property name="clazz" value="org.hisp.dhis.dataapproval.DataApprovalWorkflow" />
    <property name="sessionFactory" ref="sessionFactory" />
    <property name="cacheable" value="true" />
  </bean>

  <bean id="org.hisp.dhis.indicator.IndicatorStore" class="org.hisp.dhis.indicator.hibernate.HibernateIndicatorStore">
    <property name="clazz" value="org.hisp.dhis.indicator.Indicator" />
    <property name="sessionFactory" ref="sessionFactory" />
    <property name="cacheable" value="true" />
  </bean>

  <bean id="org.hisp.dhis.indicator.IndicatorTypeStore" class="org.hisp.dhis.common.hibernate.HibernateIdentifiableObjectStore">
    <property name="clazz" value="org.hisp.dhis.indicator.IndicatorType" />
    <property name="sessionFactory" ref="sessionFactory" />
    <property name="cacheable" value="true" />
  </bean>

  <bean id="org.hisp.dhis.indicator.IndicatorGroupStore" class="org.hisp.dhis.common.hibernate.HibernateIdentifiableObjectStore">
    <property name="clazz" value="org.hisp.dhis.indicator.IndicatorGroup" />
    <property name="sessionFactory" ref="sessionFactory" />
    <property name="cacheable" value="true" />
  </bean>

  <bean id="org.hisp.dhis.indicator.IndicatorGroupSetStore" class="org.hisp.dhis.common.hibernate.HibernateIdentifiableObjectStore">
    <property name="clazz" value="org.hisp.dhis.indicator.IndicatorGroupSet" />
    <property name="sessionFactory" ref="sessionFactory" />
    <property name="cacheable" value="true" />
  </bean>

  <bean id="org.hisp.dhis.predictor.PredictorGroupStore" class="org.hisp.dhis.common.hibernate.HibernateIdentifiableObjectStore">
    <property name="clazz" value="org.hisp.dhis.predictor.PredictorGroup" />
    <property name="sessionFactory" ref="sessionFactory" />
    <property name="cacheable" value="true" />
  </bean>

  <bean id="org.hisp.dhis.period.PeriodStore" class="org.hisp.dhis.period.hibernate.HibernatePeriodStore">
    <property name="clazz" value="org.hisp.dhis.period.Period" />
    <property name="sessionFactory" ref="sessionFactory" />
    <property name="cacheable" value="true" />
    <property name="transientIdentifiableProperties" value="true" />
  </bean>

  <bean id="org.hisp.dhis.dataset.DataSetStore" class="org.hisp.dhis.dataset.hibernate.HibernateDataSetStore">
    <property name="clazz" value="org.hisp.dhis.dataset.DataSet" />
    <property name="sessionFactory" ref="sessionFactory" />
    <property name="periodService" ref="org.hisp.dhis.period.PeriodService" />
    <property name="cacheable" value="true" />
  </bean>

  <bean id="org.hisp.dhis.dataset.LockExceptionStore" class="org.hisp.dhis.dataset.hibernate.HibernateLockExceptionStore">
    <property name="clazz" value="org.hisp.dhis.dataset.LockException" />
    <property name="sessionFactory" ref="sessionFactory" />
    <property name="jdbcTemplate" ref="jdbcTemplate" />
    <property name="dataSetStore" ref="org.hisp.dhis.dataset.DataSetStore" />
    <property name="periodService" ref="org.hisp.dhis.period.PeriodService" />
  </bean>

  <bean id="org.hisp.dhis.dataset.CompleteDataSetRegistrationStore"
    class="org.hisp.dhis.dataset.hibernate.HibernateCompleteDataSetRegistrationStore">
    <property name="clazz" value="org.hisp.dhis.dataset.CompleteDataSetRegistration" />
    <property name="sessionFactory" ref="sessionFactory" />
    <property name="periodStore" ref="org.hisp.dhis.period.PeriodStore" />
  </bean>

  <bean id="org.hisp.dhis.reservedvalue.SequentialNumberCounterStore"
    class="org.hisp.dhis.reservedvalue.hibernate.HibernateSequentialNumberCounterStore">
    <property name="sessionFactory" ref="sessionFactory" />
  </bean>

  <bean id="org.hisp.dhis.reservedvalue.ReservedValueStore" class="org.hisp.dhis.reservedvalue.hibernate.HibernateReservedValueStore">
    <property name="clazz" value="org.hisp.dhis.reservedvalue.ReservedValue" />
    <property name="sessionFactory" ref="sessionFactory" />
  </bean>

  <bean id="org.hisp.dhis.dataset.notifications.DataSetNotificationTemplateStore"
    class="org.hisp.dhis.dataset.notifications.HibernateDataSetNotificationTemplateStore">
    <property name="clazz" value="org.hisp.dhis.dataset.notifications.DataSetNotificationTemplate" />
    <property name="sessionFactory" ref="sessionFactory" />
    <property name="cacheable" value="true" />
  </bean>

  <bean id="org.hisp.dhis.expression.ExpressionStore" class="org.hisp.dhis.hibernate.HibernateGenericStore">
    <property name="clazz" value="org.hisp.dhis.expression.Expression" />
    <property name="sessionFactory" ref="sessionFactory" />
    <property name="cacheable" value="true" />
  </bean>

  <bean id="org.hisp.dhis.predictor.PredictorStore" class="org.hisp.dhis.predictor.hibernate.HibernatePredictorStore">
    <property name="clazz" value="org.hisp.dhis.predictor.Predictor" />
    <property name="sessionFactory" ref="sessionFactory" />
    <property name="periodService" ref="org.hisp.dhis.period.PeriodService" />
  </bean>

  <bean id="org.hisp.dhis.category.CategoryStore" class="org.hisp.dhis.category.hibernate.HibernateCategoryStore">
    <property name="clazz" value="org.hisp.dhis.category.Category" />
    <property name="sessionFactory" ref="sessionFactory" />
    <property name="cacheable" value="true" />
  </bean>

  <bean id="org.hisp.dhis.category.CategoryOptionStore" class="org.hisp.dhis.category.hibernate.HibernateCategoryOptionStore">
    <property name="clazz" value="org.hisp.dhis.category.CategoryOption" />
    <property name="sessionFactory" ref="sessionFactory" />
    <property name="cacheable" value="true" />
  </bean>

  <bean id="org.hisp.dhis.category.CategoryComboStore" class="org.hisp.dhis.category.hibernate.HibernateCategoryComboStore">
    <property name="clazz" value="org.hisp.dhis.category.CategoryCombo" />
    <property name="sessionFactory" ref="sessionFactory" />
    <property name="cacheable" value="true" />
  </bean>

  <bean id="org.hisp.dhis.category.CategoryOptionComboStore"
    class="org.hisp.dhis.category.hibernate.HibernateCategoryOptionComboStore">
    <property name="clazz" value="org.hisp.dhis.category.CategoryOptionCombo" />
    <property name="sessionFactory" ref="sessionFactory" />
    <property name="cacheable" value="true" />
  </bean>

  <bean id="org.hisp.dhis.category.CategoryOptionGroupStore" class="org.hisp.dhis.category.hibernate.HibernateCategoryOptionGroupStore">
    <property name="clazz" value="org.hisp.dhis.category.CategoryOptionGroup" />
    <property name="sessionFactory" ref="sessionFactory" />
    <property name="cacheable" value="true" />
  </bean>

  <bean id="org.hisp.dhis.category.CategoryOptionGroupSetStore"
    class="org.hisp.dhis.category.hibernate.HibernateCategoryOptionGroupSetStore">
    <property name="clazz" value="org.hisp.dhis.category.CategoryOptionGroupSet" />
    <property name="sessionFactory" ref="sessionFactory" />
    <property name="cacheable" value="true" />
  </bean>

  <bean id="org.hisp.dhis.dataset.SectionStore" class="org.hisp.dhis.dataset.hibernate.HibernateSectionStore">
    <property name="clazz" value="org.hisp.dhis.dataset.Section" />
    <property name="sessionFactory" ref="sessionFactory" />
    <property name="cacheable" value="true" />
  </bean>

  <bean id="org.hisp.dhis.organisationunit.OrganisationUnitLevelStore"
    class="org.hisp.dhis.organisationunit.hibernate.HibernateOrganisationUnitLevelStore">
    <property name="clazz" value="org.hisp.dhis.organisationunit.OrganisationUnitLevel" />
    <property name="sessionFactory" ref="sessionFactory" />
    <property name="jdbcTemplate" ref="jdbcTemplate" />
    <property name="cacheable" value="true" />
  </bean>

  <bean id="org.hisp.dhis.organisationunit.OrganisationUnitStore"
    class="org.hisp.dhis.organisationunit.hibernate.HibernateOrganisationUnitStore">
    <property name="clazz" value="org.hisp.dhis.organisationunit.OrganisationUnit" />
    <property name="sessionFactory" ref="sessionFactory" />
    <property name="jdbcTemplate" ref="jdbcTemplate" />
    <property name="cacheable" value="true" />
  </bean>

  <bean id="org.hisp.dhis.organisationunit.OrganisationUnitGroupStore"
    class="org.hisp.dhis.organisationunit.hibernate.HibernateOrganisationUnitGroupStore">
    <property name="clazz" value="org.hisp.dhis.organisationunit.OrganisationUnitGroup" />
    <property name="sessionFactory" ref="sessionFactory" />
    <property name="cacheable" value="true" />
  </bean>

  <bean id="org.hisp.dhis.organisationunit.OrganisationUnitGroupSetStore"
    class="org.hisp.dhis.organisationunit.hibernate.HibernateOrganisationUnitGroupSetStore">
    <property name="clazz" value="org.hisp.dhis.organisationunit.OrganisationUnitGroupSet" />
    <property name="sessionFactory" ref="sessionFactory" />
    <property name="cacheable" value="true" />
  </bean>

  <bean id="org.hisp.dhis.datavalue.DataValueAuditStore" class="org.hisp.dhis.datavalue.hibernate.HibernateDataValueAuditStore">
    <property name="sessionFactory" ref="sessionFactory" />
    <property name="periodStore" ref="org.hisp.dhis.period.PeriodStore" />
    <property name="clazz" value="org.hisp.dhis.datavalue.DataValueAudit" />
  </bean>

  <bean id="org.hisp.dhis.user.UserStore" class="org.hisp.dhis.user.hibernate.HibernateUserStore">
    <property name="sessionFactory" ref="sessionFactory" />
    <property name="clazz" value="org.hisp.dhis.user.User" />
    <property name="cacheable" value="true" />
  </bean>

  <bean id="org.hisp.dhis.user.CurrentUserStore" class="org.hisp.dhis.user.hibernate.HibernateCurrentUserStore" />

  <bean id="org.hisp.dhis.user.UserSettingStore" class="org.hisp.dhis.user.hibernate.HibernateUserSettingStore">
    <property name="sessionFactory" ref="sessionFactory" />
  </bean>

  <bean id="org.hisp.dhis.user.UserAuthorityGroupStore" class="org.hisp.dhis.user.hibernate.HibernateUserAuthorityGroupStore">
    <property name="sessionFactory" ref="sessionFactory" />
    <property name="clazz" value="org.hisp.dhis.user.UserAuthorityGroup" />
    <property name="cacheable" value="true" />
  </bean>

  <bean id="org.hisp.dhis.user.UserCredentialsStore" class="org.hisp.dhis.user.hibernate.HibernateUserCredentialsStore">
    <property name="clazz" value="org.hisp.dhis.user.UserCredentials" />
    <property name="sessionFactory" ref="sessionFactory" />
    <property name="cacheable" value="true" />
  </bean>

  <bean id="org.hisp.dhis.user.UserGroupStore" class="org.hisp.dhis.common.hibernate.HibernateIdentifiableObjectStore">
    <property name="clazz" value="org.hisp.dhis.user.UserGroup" />
    <property name="sessionFactory" ref="sessionFactory" />
    <property name="cacheable" value="true" />
  </bean>

  <bean id="org.hisp.dhis.user.UserGroupAccessStore" class="org.hisp.dhis.hibernate.HibernateGenericStore">
    <property name="clazz" value="org.hisp.dhis.user.UserGroupAccess" />
    <property name="sessionFactory" ref="sessionFactory" />
  </bean>

  <bean id="org.hisp.dhis.user.UserAccessStore" class="org.hisp.dhis.hibernate.HibernateGenericStore">
    <property name="clazz" value="org.hisp.dhis.user.UserAccess" />
    <property name="sessionFactory" ref="sessionFactory" />
  </bean>

  <bean id="org.hisp.dhis.user.PasswordValidationService" class="org.hisp.dhis.user.DefaultPasswordValidationService" />

  <bean id="org.hisp.dhis.user.PasswordHistoryValidationRule" class="org.hisp.dhis.user.PasswordHistoryValidationRule" />

  <bean id="org.hisp.dhis.user.PasswordLengthValidationRule" class="org.hisp.dhis.user.PasswordLengthValidationRule" />

  <bean id="org.hisp.dhis.user.DigitPatternValidationRule" class="org.hisp.dhis.user.DigitPatternValidationRule" />

  <bean id="org.hisp.dhis.user.UpperCasePatternValidationRule" class="org.hisp.dhis.user.UpperCasePatternValidationRule" />

  <bean id="org.hisp.dhis.user.SpecialCharacterValidationRule" class="org.hisp.dhis.user.SpecialCharacterValidationRule" />

  <bean id="org.hisp.dhis.user.PasswordDictionaryValidationRule" class="org.hisp.dhis.user.PasswordDictionaryValidationRule" />

  <bean id="org.hisp.dhis.user.UserParameterValidationRule" class="org.hisp.dhis.user.UserParameterValidationRule" />

  <bean id="org.hisp.dhis.message.MessageConversationStore" class="org.hisp.dhis.message.hibernate.HibernateMessageConversationStore">
    <property name="clazz" value="org.hisp.dhis.message.MessageConversation" />
    <property name="sessionFactory" ref="sessionFactory" />
    <property name="jdbcTemplate" ref="jdbcTemplate" />
    <property name="statementBuilder" ref="statementBuilder" />
  </bean>

  <bean id="org.hisp.dhis.configuration.ConfigurationStore" class="org.hisp.dhis.hibernate.HibernateGenericStore">
    <property name="sessionFactory" ref="sessionFactory" />
    <property name="clazz" value="org.hisp.dhis.configuration.Configuration" />
    <property name="cacheable" value="true" />
  </bean>

  <bean id="org.hisp.dhis.constant.ConstantStore" class="org.hisp.dhis.common.hibernate.HibernateIdentifiableObjectStore">
    <property name="sessionFactory" ref="sessionFactory" />
    <property name="clazz" value="org.hisp.dhis.constant.Constant" />
    <property name="cacheable" value="true" />
  </bean>

  <bean id="org.hisp.dhis.scheduling.JobConfigurationStore" class="org.hisp.dhis.common.hibernate.HibernateIdentifiableObjectStore">
    <property name="sessionFactory" ref="sessionFactory" />
    <property name="clazz" value="org.hisp.dhis.scheduling.JobConfiguration" />
    <property name="cacheable" value="true" />
  </bean>

  <bean id="org.hisp.dhis.deletedobject.DeletedObjectStore" class="org.hisp.dhis.deletedobject.hibernate.HibernateDeletedObjectStore" />

  <bean id="org.hisp.dhis.version.VersionStore" class="org.hisp.dhis.version.hibernate.HibernateVersionStore">
    <property name="sessionFactory" ref="sessionFactory" />
    <property name="clazz" value="org.hisp.dhis.version.Version" />
    <property name="cacheable" value="true" />
  </bean>

  <bean id="org.hisp.dhis.metadata.version.MetadataVersionStore"
    class="org.hisp.dhis.metadata.version.hibernate.HibernateMetadataVersionStore">
    <property name="sessionFactory" ref="sessionFactory" />
    <property name="clazz" value="org.hisp.dhis.metadata.version.MetadataVersion" />
  </bean>

  <bean id="org.hisp.dhis.attribute.AttributeStore" class="org.hisp.dhis.attribute.hibernate.HibernateAttributeStore">
    <property name="sessionFactory" ref="sessionFactory" />
    <property name="clazz" value="org.hisp.dhis.attribute.Attribute" />
    <property name="cacheable" value="true" />
  </bean>

  <bean id="org.hisp.dhis.attribute.AttributeValueStore" class="org.hisp.dhis.attribute.hibernate.HibernateAttributeValueStore">
    <property name="sessionFactory" ref="sessionFactory" />
    <property name="clazz" value="org.hisp.dhis.attribute.AttributeValue" />
    <property name="cacheable" value="true" />
  </bean>

  <bean id="org.hisp.dhis.option.OptionSetStore" class="org.hisp.dhis.common.hibernate.HibernateIdentifiableObjectStore">
    <property name="clazz" value="org.hisp.dhis.option.OptionSet" />
    <property name="sessionFactory" ref="sessionFactory" />
    <property name="cacheable" value="true" />
  </bean>

  <bean id="org.hisp.dhis.option.OptionStore" class="org.hisp.dhis.option.hibernate.HibernateOptionStore">
    <property name="clazz" value="org.hisp.dhis.option.Option" />
    <property name="sessionFactory" ref="sessionFactory" />
    <property name="cacheable" value="true" />
  </bean>

  <bean id="org.hisp.dhis.option.OptionGroupStore" class="org.hisp.dhis.option.hibernate.HibernateOptionGroupStore">
    <property name="clazz" value="org.hisp.dhis.option.OptionGroup" />
    <property name="sessionFactory" ref="sessionFactory" />
    <property name="cacheable" value="true" />
  </bean>

  <bean id="org.hisp.dhis.option.OptionGroupSetStore" class="org.hisp.dhis.option.hibernate.HibernateOptionGroupSetStore">
    <property name="clazz" value="org.hisp.dhis.option.OptionGroupSet" />
    <property name="sessionFactory" ref="sessionFactory" />
    <property name="cacheable" value="true" />
  </bean>

  <bean id="org.hisp.dhis.mapping.MapStore" class="org.hisp.dhis.mapping.hibernate.HibernateMapStore">
    <property name="clazz" value="org.hisp.dhis.mapping.Map" />
    <property name="sessionFactory" ref="sessionFactory" />
    <property name="cacheable" value="true" />
  </bean>

  <bean id="org.hisp.dhis.mapping.MapViewStore"
    class="org.hisp.dhis.mapping.hibernate.HibernateMapViewStore">
    <property name="clazz" value="org.hisp.dhis.mapping.MapView" />
    <property name="sessionFactory" ref="sessionFactory" />
    <property name="cacheable" value="true" />
  </bean>

  <bean id="org.hisp.dhis.mapping.ExternalMapLayerStore"
    class="org.hisp.dhis.mapping.hibernate.HibernateExternalMapLayerStore">
    <property name="clazz" value="org.hisp.dhis.mapping.ExternalMapLayer" />
    <property name="sessionFactory" ref="sessionFactory" />
  </bean>

  <bean id="org.hisp.dhis.legend.LegendSetStore"
    class="org.hisp.dhis.common.hibernate.HibernateIdentifiableObjectStore">
    <property name="clazz" value="org.hisp.dhis.legend.LegendSet" />
    <property name="sessionFactory" ref="sessionFactory" />
    <property name="cacheable" value="true" />
  </bean>

  <bean id="org.hisp.dhis.sms.hibernate.IncomingSmsStore"
    class="org.hisp.dhis.sms.hibernate.HibernateIncomingSmsStore">
    <property name="sessionFactory" ref="sessionFactory" />
    <property name="clazz" value="org.hisp.dhis.sms.incoming.IncomingSms" />
  </bean>

  <bean id="org.hisp.dhis.sms.hibernate.OutboundSmsStore"
    class="org.hisp.dhis.sms.hibernate.HibernateOutboundSmsStore">
    <property name="clazz" value="org.hisp.dhis.sms.outbound.OutboundSms" />
    <property name="sessionFactory" ref="sessionFactory" />
  </bean>

  <bean id="org.hisp.dhis.i18n.I18nLocaleStore" class="org.hisp.dhis.i18n.hibernate.HibernateI18nLocaleStore">
    <property name="clazz" value="org.hisp.dhis.i18n.locale.I18nLocale" />
    <property name="sessionFactory" ref="sessionFactory" />
  </bean>

  <bean id="org.hisp.dhis.program.ProgramIndicatorStore"
    class="org.hisp.dhis.program.hibernate.HibernateProgramIndicatorStore">
    <property name="clazz" value="org.hisp.dhis.program.ProgramIndicator" />
    <property name="sessionFactory" ref="sessionFactory" />
    <property name="cacheable" value="true" />
  </bean>

  <bean id="org.hisp.dhis.program.ProgramIndicatorGroupStore" class="org.hisp.dhis.common.hibernate.HibernateIdentifiableObjectStore">
    <property name="clazz" value="org.hisp.dhis.program.ProgramIndicatorGroup" />
    <property name="sessionFactory" ref="sessionFactory" />
    <property name="cacheable" value="true" />
  </bean>

  <bean id="org.hisp.dhis.relationship.RelationshipStore"
    class="org.hisp.dhis.relationship.hibernate.HibernateRelationshipStore">
    <property name="clazz" value="org.hisp.dhis.relationship.Relationship" />
    <property name="sessionFactory" ref="sessionFactory" />
    <property name="cacheable" value="true" />
  </bean>

  <bean id="org.hisp.dhis.relationship.RelationshipTypeStore"
    class="org.hisp.dhis.relationship.hibernate.HibernateRelationshipTypeStore">
    <property name="clazz" value="org.hisp.dhis.relationship.RelationshipType" />
    <property name="sessionFactory" ref="sessionFactory" />
    <property name="cacheable" value="true" />
  </bean>

  <bean id="org.hisp.dhis.program.ProgramStageInstanceStore"
    class="org.hisp.dhis.program.hibernate.HibernateProgramStageInstanceStore">
    <property name="clazz" value="org.hisp.dhis.program.ProgramStageInstance" />
    <property name="sessionFactory" ref="sessionFactory" />
    <property name="jdbcTemplate" ref="jdbcTemplate" />
  </bean>
  
  <bean id="org.hisp.dhis.program.EventSyncService"
    class="org.hisp.dhis.program.DefaultEventSyncService">
    <property name="eventSyncStore" ref="org.hisp.dhis.program.EventSyncStore" />
  </bean>
  
  <bean id="org.hisp.dhis.program.EventSyncStore"
    class="org.hisp.dhis.program.hibernate.HibernateEventSyncStore">
    <property name="sessionFactory" ref="sessionFactory" />
  </bean>

  <bean id="org.hisp.dhis.program.ProgramInstanceStore"
    class="org.hisp.dhis.program.hibernate.HibernateProgramInstanceStore">
    <property name="clazz" value="org.hisp.dhis.program.ProgramInstance" />
    <property name="sessionFactory" ref="sessionFactory" />
    <property name="jdbcTemplate" ref="jdbcTemplate" />
    <property name="cacheable" value="true" />
  </bean>

  <bean id="org.hisp.dhis.program.ProgramStageStore"
    class="org.hisp.dhis.program.hibernate.HibernateProgramStageStore">
    <property name="clazz" value="org.hisp.dhis.program.ProgramStage" />
    <property name="sessionFactory" ref="sessionFactory" />
    <property name="cacheable" value="true" />
  </bean>

  <bean id="org.hisp.dhis.program.ProgramStageSectionStore"
    class="org.hisp.dhis.program.hibernate.HibernateProgramStageSectionStore">
    <property name="clazz" value="org.hisp.dhis.program.ProgramStageSection" />
    <property name="sessionFactory" ref="sessionFactory" />
    <property name="cacheable" value="true" />
  </bean>

  <bean id="org.hisp.dhis.program.ProgramSectionStore"
    class="org.hisp.dhis.program.hibernate.HibernateProgramSectionStore">
    <property name="clazz" value="org.hisp.dhis.program.ProgramSection" />
    <property name="sessionFactory" ref="sessionFactory" />
    <property name="cacheable" value="true" />
  </bean>

  <bean id="org.hisp.dhis.program.ProgramStore"
    class="org.hisp.dhis.program.hibernate.HibernateProgramStore">
    <property name="clazz" value="org.hisp.dhis.program.Program" />
    <property name="sessionFactory" ref="sessionFactory" />
    <property name="cacheable" value="true" />
  </bean>

  <bean id="org.hisp.dhis.program.ProgramTrackedEntityAttributeStore"
    class="org.hisp.dhis.program.hibernate.HibernateProgramTrackedEntityAttributeStore">
    <property name="clazz" value="org.hisp.dhis.program.ProgramTrackedEntityAttribute" />
    <property name="sessionFactory" ref="sessionFactory" />
    <property name="cacheable" value="true" />
  </bean>

  <bean id="org.hisp.dhis.program.ProgramTrackedEntityAttributeGroupStore"
    class="org.hisp.dhis.program.hibernate.HibernateProgramTrackedEntityAttributeGroupStore">
    <property name="clazz" value="org.hisp.dhis.program.ProgramTrackedEntityAttributeGroup" />
    <property name="sessionFactory" ref="sessionFactory" />
    <property name="cacheable" value="true" />
  </bean>

  <bean id="org.hisp.dhis.program.ProgramMessageStore"
    class="org.hisp.dhis.program.hibernate.HibernateProgramMessageStore">
    <property name="clazz" value="org.hisp.dhis.program.message.ProgramMessage" />
    <property name="jdbcTemplate" ref="jdbcTemplate" />
    <property name="sessionFactory" ref="sessionFactory" />
    <property name="cacheable" value="true" />
  </bean>

  <bean id="org.hisp.dhis.program.ProgramExpressionStore"
    class="org.hisp.dhis.hibernate.HibernateGenericStore">
    <property name="clazz" value="org.hisp.dhis.program.ProgramExpression" />
    <property name="sessionFactory" ref="sessionFactory" />
  </bean>

  <bean id="org.hisp.dhis.trackedentityfilter.TrackedEntityInstanceFilterStore"
    class="org.hisp.dhis.trackedentityfilter.hibernate.HibernateTrackedEntityInstanceFilterStore">
    <property name="clazz" value="org.hisp.dhis.trackedentityfilter.TrackedEntityInstanceFilter" />
    <property name="sessionFactory" ref="sessionFactory" />
    <property name="cacheable" value="true" />
  </bean>

  <bean id="org.hisp.dhis.trackedentity.TrackedEntityInstanceStore"
    class="org.hisp.dhis.trackedentity.hibernate.HibernateTrackedEntityInstanceStore">
    <property name="clazz" value="org.hisp.dhis.trackedentity.TrackedEntityInstance" />
    <property name="sessionFactory" ref="sessionFactory" />
    <property name="jdbcTemplate" ref="jdbcTemplate" />
    <property name="statementBuilder" ref="statementBuilder" />
    <property name="organisationUnitStore" ref="org.hisp.dhis.organisationunit.OrganisationUnitStore"/>
   </bean>

  <bean id="org.hisp.dhis.trackedentity.TrackedEntityProgramOwnerStore"
    class="org.hisp.dhis.trackedentity.hibernate.HibernateTrackedEntityProgramOwnerStore">
    <property name="clazz" value="org.hisp.dhis.trackedentity.TrackedEntityProgramOwner" />
    <property name="sessionFactory" ref="sessionFactory" />
    <property name="jdbcTemplate" ref="jdbcTemplate" />
  </bean>

  <bean id="org.hisp.dhis.trackedentity.TrackedEntityAttributeStore"
    class="org.hisp.dhis.trackedentity.hibernate.HibernateTrackedEntityAttributeStore">
    <property name="clazz" value="org.hisp.dhis.trackedentity.TrackedEntityAttribute" />
    <property name="sessionFactory" ref="sessionFactory" />
    <property name="cacheable" value="true" />
  </bean>

  <bean id="org.hisp.dhis.trackedentityattributevalue.TrackedEntityAttributeValueStore"
    class="org.hisp.dhis.trackedentityattributevalue.hibernate.HibernateTrackedEntityAttributeValueStore">
    <property name="clazz" value="org.hisp.dhis.trackedentityattributevalue.TrackedEntityAttributeValue" />
    <property name="sessionFactory" ref="sessionFactory" />
    <property name="jdbcTemplate" ref="jdbcTemplate" />
  </bean>

  <bean id="org.hisp.dhis.trackedentitydatavalue.TrackedEntityDataValueStore"
    class="org.hisp.dhis.trackedentitydatavalue.hibernate.HibernateTrackedEntityDataValueStore">
    <property name="clazz" value="org.hisp.dhis.trackedentitydatavalue.TrackedEntityDataValue" />
    <property name="sessionFactory" ref="sessionFactory" />
  </bean>

  <bean id="org.hisp.dhis.trackedentitydatavalue.TrackedEntityDataValueAuditStore"
    class="org.hisp.dhis.trackedentitydatavalue.hibernate.HibernateTrackedEntityDataValueAuditStore">
    <property name="sessionFactory" ref="sessionFactory" />
  </bean>

  <bean id="org.hisp.dhis.trackedentityattributevalue.TrackedEntityAttributeValueAuditStore"
    class="org.hisp.dhis.trackedentityattributevalue.hibernate.HibernateTrackedEntityAttributeValueAuditStore">
    <property name="sessionFactory" ref="sessionFactory" />
  </bean>

  <bean id="org.hisp.dhis.trackedentitydatavalue.TrackedEntityDataValueAuditService"
    class="org.hisp.dhis.trackedentitydatavalue.DefaultTrackedEntityDataValueAuditService" />

  <bean id="org.hisp.dhis.trackedentityattributevalue.TrackedEntityAttributeValueAuditService"
    class="org.hisp.dhis.trackedentityattributevalue.DefaultTrackedEntityAttributeValueAuditService" />

  <bean id="org.hisp.dhis.trackedentity.TrackedEntityInstanceAuditService"
    class="org.hisp.dhis.trackedentity.DefaultTrackedEntityInstanceAuditService" />

  <bean id="org.hisp.dhis.trackedentity.TrackedEntityInstanceAuditStore"
    class="org.hisp.dhis.trackedentity.hibernate.HibernateTrackedEntityInstanceAuditStore">
    <property name="clazz" value="org.hisp.dhis.trackedentity.TrackedEntityInstanceAudit" />
    <property name="sessionFactory" ref="sessionFactory" />
  </bean>

  <bean id="org.hisp.dhis.program.ProgramInstanceAuditService"
    class="org.hisp.dhis.program.DefaultProgramInstanceAuditService" />

  <bean id="org.hisp.dhis.program.ProgramTempOwnershipAuditService"
    class="org.hisp.dhis.program.DefaultProgramTempOwnershipAuditService" />

  <bean id="org.hisp.dhis.program.ProgramInstanceAuditStore"
    class="org.hisp.dhis.program.hibernate.HibernateProgramInstanceAuditStore">
    <property name="clazz" value="org.hisp.dhis.program.ProgramInstanceAudit" />
    <property name="sessionFactory" ref="sessionFactory" />
  </bean>

  <bean id="org.hisp.dhis.program.ProgramTempOwnershipAuditStore"
    class="org.hisp.dhis.program.hibernate.HibernateProgramTempOwnershipAuditStore">
    <property name="clazz" value="org.hisp.dhis.program.ProgramTempOwnershipAudit" />
    <property name="sessionFactory" ref="sessionFactory" />
  </bean>

  <bean id="org.hisp.dhis.program.ProgramOwnershipHistoryStore"
    class="org.hisp.dhis.program.hibernate.HibernateProgramOwnershipHistoryStore">
    <property name="sessionFactory" ref="sessionFactory" />
  </bean>

  <bean id="org.hisp.dhis.program.ProgramOwnershipHistoryService"
    class="org.hisp.dhis.program.DefaultProgramOwnershipHistoryService" />

  <bean id="org.hisp.dhis.program.ProgramStageDataElementStore"
    class="org.hisp.dhis.program.hibernate.HibernateProgramStageDataElementStore">
    <property name="clazz" value="org.hisp.dhis.program.ProgramStageDataElement" />
    <property name="sessionFactory" ref="sessionFactory" />
  </bean>

  <bean id="org.hisp.dhis.trackedentity.TrackedEntityTypeStore"
    class="org.hisp.dhis.trackedentity.hibernate.HibernateTrackedEntityTypeStore">
    <property name="clazz" value="org.hisp.dhis.trackedentity.TrackedEntityType" />
    <property name="sessionFactory" ref="sessionFactory" />
    <property name="cacheable" value="true" />
  </bean>

  <bean id="org.hisp.dhis.sqlview.SqlViewStore" class="org.hisp.dhis.sqlview.hibernate.HibernateSqlViewStore">
    <property name="clazz" value="org.hisp.dhis.sqlview.SqlView" />
    <property name="sessionFactory" ref="sessionFactory" />
    <property name="jdbcTemplate" ref="jdbcTemplate" />
    <property name="readOnlyJdbcTemplate" ref="readOnlyJdbcTemplate" />
    <property name="statementBuilder" ref="statementBuilder" />    
    <property name="systemSettingManager" ref="org.hisp.dhis.setting.SystemSettingManager" />
  </bean>

  <bean id="org.hisp.dhis.eventreport.EventReportStore"
    class="org.hisp.dhis.common.hibernate.HibernateAnalyticalObjectStore">
    <property name="clazz" value="org.hisp.dhis.eventreport.EventReport" />
    <property name="sessionFactory" ref="sessionFactory" />
    <property name="cacheable" value="true" />
  </bean>

  <bean id="org.hisp.dhis.eventchart.EventChartStore"
    class="org.hisp.dhis.common.hibernate.HibernateAnalyticalObjectStore">
    <property name="clazz" value="org.hisp.dhis.eventchart.EventChart" />
    <property name="sessionFactory" ref="sessionFactory" />
    <property name="cacheable" value="true" />
  </bean>

  <bean id="org.hisp.dhis.sms.command.hibernate.SMSCommandStore"
    class="org.hisp.dhis.sms.command.hibernate.HibernateSMSCommandStore">
    <property name="clazz" value="org.hisp.dhis.sms.command.SMSCommand" />
    <property name="sessionFactory" ref="sessionFactory" />
    <property name="cacheable" value="true" />
  </bean>

  <bean id="org.hisp.dhis.color.ColorSetStore" class="org.hisp.dhis.common.hibernate.HibernateIdentifiableObjectStore">
    <property name="clazz" value="org.hisp.dhis.color.ColorSet" />
    <property name="sessionFactory" ref="sessionFactory" />
    <property name="cacheable" value="true" />
  </bean>

  <bean id="org.hisp.dhis.keyjsonvalue.KeyJsonValueStore" class="org.hisp.dhis.keyjsonvalue.hibernate.HibernateKeyJsonValueStore">
    <property name="clazz" value="org.hisp.dhis.keyjsonvalue.KeyJsonValue" />
    <property name="sessionFactory" ref="sessionFactory" />
  </bean>

  <bean id="org.hisp.dhis.userkeyjsonvalue.UserKeyJsonValueStore"
    class="org.hisp.dhis.userkeyjsonvalue.hibernate.HibernateUserKeyJsonValueStore">
    <property name="clazz" value="org.hisp.dhis.userkeyjsonvalue.UserKeyJsonValue" />
    <property name="sessionFactory" ref="sessionFactory" />
  </bean>

  <bean id="org.hisp.dhis.fileresource.FileResourceStore" class="org.hisp.dhis.common.hibernate.HibernateIdentifiableObjectStore">
    <property name="clazz" value="org.hisp.dhis.fileresource.FileResource" />
    <property name="sessionFactory" ref="sessionFactory" />
  </bean>

  <bean id="org.hisp.dhis.fileresource.ExternalFileResourceStore"
    class="org.hisp.dhis.fileresource.hibernate.HibernateExternalFileResourceStore">
    <property name="clazz" value="org.hisp.dhis.fileresource.ExternalFileResource" />
    <property name="sessionFactory" ref="sessionFactory" />
  </bean>

  <bean id="org.hisp.dhis.fileresource.FileResourceContentStore" class="org.hisp.dhis.fileresource.JCloudsFileResourceContentStore">
    <property name="configurationProvider" ref="dhisConfigurationProvider" />
    <property name="locationManager" ref="locationManager" />
  </bean>

  <bean id="org.hisp.dhis.analytics.AnalyticsTableHookStore" class="org.hisp.dhis.analytics.hibernate.HibernateAnalyticsTableHookStore">
    <property name="clazz" value="org.hisp.dhis.analytics.AnalyticsTableHook" />
    <property name="sessionFactory" ref="sessionFactory" />
    <property name="jdbcTemplate" ref="jdbcTemplate" />
  </bean>

  <!-- File resource jobs -->

  <bean id="org.hisp.dhis.fileresource.FileResourceUploadCallback" class="org.hisp.dhis.fileresource.FileResourceUploadCallback" />

  <bean id="fileResourceCleanUpJob" class="org.hisp.dhis.fileresource.FileResourceCleanUpJob" />

  <!-- Service definitions -->

  <bean id="org.hisp.dhis.dataelement.DataElementGroupService" class="org.hisp.dhis.dataelement.DefaultDataElementGroupService" />

  <bean id="org.hisp.dhis.indicator.IndicatorGroupService" class="org.hisp.dhis.indicator.DefaultIndicatorGroupService">
    <property name="indicatorGroupStore" ref="org.hisp.dhis.indicator.IndicatorGroupStore" />
  </bean>

  <bean id="org.hisp.dhis.dimension.DimensionService" class="org.hisp.dhis.dimension.DefaultDimensionService" />

  <bean id="org.hisp.dhis.fileresource.FileResourceService" class="org.hisp.dhis.fileresource.DefaultFileResourceService">
    <property name="fileResourceStore" ref="org.hisp.dhis.fileresource.FileResourceStore" />
    <property name="fileResourceContentStore" ref="org.hisp.dhis.fileresource.FileResourceContentStore" />
    <property name="schedulingManager" ref="org.hisp.dhis.scheduling.SchedulingManager" />
    <property name="uploadCallback" ref="org.hisp.dhis.fileresource.FileResourceUploadCallback" />
  </bean>

  <bean id="org.hisp.dhis.fileresource.ExternalFileResourceService" class="org.hisp.dhis.fileresource.DefaultExternalFileResourceService">
    <property name="externalFileResourceStore" ref="org.hisp.dhis.fileresource.ExternalFileResourceStore" />
  </bean>

  <bean id="org.hisp.dhis.datavalue.DataValueService" class="org.hisp.dhis.datavalue.DefaultDataValueService">
    <property name="dataValueStore" ref="org.hisp.dhis.datavalue.DataValueStore" />
    <property name="dataValueAuditService" ref="org.hisp.dhis.datavalue.DataValueAuditService" />
    <property name="currentUserService" ref="org.hisp.dhis.user.CurrentUserService" />
    <property name="categoryService" ref="org.hisp.dhis.category.CategoryService" />
  </bean>

  <bean id="org.hisp.dhis.datavalue.DataValueAuditService" class="org.hisp.dhis.datavalue.DefaultDataValueAuditService">
    <property name="dataValueAuditStore" ref="org.hisp.dhis.datavalue.DataValueAuditStore" />
  </bean>

  <bean id="org.hisp.dhis.dataapproval.DataApprovalService" class="org.hisp.dhis.dataapproval.DefaultDataApprovalService">
    <property name="dataApprovalStore" ref="org.hisp.dhis.dataapproval.DataApprovalStore" />
    <property name="dataApprovalAuditStore" ref="org.hisp.dhis.dataapproval.DataApprovalAuditStore" />
    <property name="workflowStore" ref="org.hisp.dhis.dataapproval.DataApprovalWorkflowStore" />
    <property name="dataApprovalLevelService" ref="org.hisp.dhis.dataapproval.DataApprovalLevelService" />
    <property name="currentUserService" ref="org.hisp.dhis.user.CurrentUserService" />
    <property name="organisationUnitService" ref="org.hisp.dhis.organisationunit.OrganisationUnitService" />
    <property name="periodService" ref="org.hisp.dhis.period.PeriodService" />
    <property name="systemSettingManager" ref="org.hisp.dhis.setting.SystemSettingManager" />
  </bean>

  <bean id="org.hisp.dhis.dataapproval.DataApprovalAuditService" class="org.hisp.dhis.dataapproval.DefaultDataApprovalAuditService">
    <property name="dataApprovalAuditStore" ref="org.hisp.dhis.dataapproval.DataApprovalAuditStore" />
    <property name="dataApprovalLevelService" ref="org.hisp.dhis.dataapproval.DataApprovalLevelService" />
    <property name="currentUserService" ref="org.hisp.dhis.user.CurrentUserService" />
    <property name="aclService" ref="org.hisp.dhis.security.acl.AclService" />
  </bean>

  <bean id="org.hisp.dhis.dataapproval.DataApprovalLevelService" class="org.hisp.dhis.dataapproval.DefaultDataApprovalLevelService">
    <property name="dataApprovalLevelStore" ref="org.hisp.dhis.dataapproval.DataApprovalLevelStore" />
    <property name="organisationUnitService" ref="org.hisp.dhis.organisationunit.OrganisationUnitService" />
    <property name="categoryService" ref="org.hisp.dhis.category.CategoryService" />
    <property name="currentUserService" ref="org.hisp.dhis.user.CurrentUserService" />
    <property name="aclService" ref="org.hisp.dhis.security.acl.AclService" />
  </bean>

  <bean id="org.hisp.dhis.dataelement.DataElementService" class="org.hisp.dhis.dataelement.DefaultDataElementService">
    <property name="dataElementStore" ref="org.hisp.dhis.dataelement.DataElementStore" />
    <property name="dataElementGroupStore" ref="org.hisp.dhis.dataelement.DataElementGroupStore" />
    <property name="dataElementGroupSetStore" ref="org.hisp.dhis.dataelement.DataElementGroupSetStore" />
  </bean>

  <bean id="org.hisp.dhis.indicator.IndicatorService" class="org.hisp.dhis.indicator.DefaultIndicatorService">
    <property name="indicatorStore" ref="org.hisp.dhis.indicator.IndicatorStore" />
    <property name="indicatorTypeStore" ref="org.hisp.dhis.indicator.IndicatorTypeStore" />
    <property name="indicatorGroupStore" ref="org.hisp.dhis.indicator.IndicatorGroupStore" />
    <property name="indicatorGroupSetStore" ref="org.hisp.dhis.indicator.IndicatorGroupSetStore" />
  </bean>

  <bean id="org.hisp.dhis.period.PeriodService" class="org.hisp.dhis.period.DefaultPeriodService">
    <property name="periodStore" ref="org.hisp.dhis.period.PeriodStore" />
  </bean>

  <bean id="org.hisp.dhis.dataset.DataSetService" class="org.hisp.dhis.dataset.DefaultDataSetService">
    <property name="dataSetStore" ref="org.hisp.dhis.dataset.DataSetStore" />
    <property name="lockExceptionStore" ref="org.hisp.dhis.dataset.LockExceptionStore" />
    <property name="dataApprovalService" ref="org.hisp.dhis.dataapproval.DataApprovalService" />
  </bean>

  <bean id="org.hisp.dhis.dataset.CompleteDataSetRegistrationService"
    class="org.hisp.dhis.dataset.DefaultCompleteDataSetRegistrationService">
    <property name="completeDataSetRegistrationStore" ref="org.hisp.dhis.dataset.CompleteDataSetRegistrationStore" />
    <property name="categoryService" ref="org.hisp.dhis.category.CategoryService" />
  </bean>

  <bean id="org.hisp.dhis.dataset.SectionService" class="org.hisp.dhis.dataset.DefaultSectionService">
    <property name="sectionStore" ref="org.hisp.dhis.dataset.SectionStore" />
    <property name="dataSetService" ref="org.hisp.dhis.dataset.DataSetService" />
  </bean>

  <bean id="org.hisp.dhis.dataentryform.DataEntryFormService" class="org.hisp.dhis.dataentryform.DefaultDataEntryFormService">
    <property name="dataEntryFormStore" ref="org.hisp.dhis.dataentryform.DataEntryFormStore" />
    <property name="dataElementService" ref="org.hisp.dhis.dataelement.DataElementService" />
    <property name="indicatorService" ref="org.hisp.dhis.indicator.IndicatorService" />
    <property name="idObjectManager" ref="org.hisp.dhis.common.IdentifiableObjectManager" />
  </bean>

  <bean id="org.hisp.dhis.expression.ExpressionService" class="org.hisp.dhis.expression.DefaultExpressionService">
    <property name="expressionStore" ref="org.hisp.dhis.expression.ExpressionStore" />
    <property name="dataElementService" ref="org.hisp.dhis.dataelement.DataElementService" />
    <property name="constantService" ref="org.hisp.dhis.constant.ConstantService" />
    <property name="categoryService" ref="org.hisp.dhis.category.CategoryService" />
    <property name="organisationUnitGroupService" ref="org.hisp.dhis.organisationunit.OrganisationUnitGroupService" />
    <property name="dimensionService" ref="org.hisp.dhis.dimension.DimensionService" />
    <property name="idObjectManager" ref="org.hisp.dhis.common.IdentifiableObjectManager" />
  </bean>

  <bean id="validationNotificationMessageRenderer" class="org.hisp.dhis.notification.ValidationNotificationMessageRenderer" />

  <bean id="org.hisp.dhis.category.CategoryManager" class="org.hisp.dhis.category.DefaultCategoryManager" />

  <bean id="org.hisp.dhis.category.CategoryService" class="org.hisp.dhis.dataelement.DefaultCategoryService">
    <property name="categoryStore" ref="org.hisp.dhis.category.CategoryStore" />
    <property name="categoryOptionStore" ref="org.hisp.dhis.category.CategoryOptionStore" />
    <property name="categoryComboStore" ref="org.hisp.dhis.category.CategoryComboStore" />
    <property name="categoryOptionComboStore" ref="org.hisp.dhis.category.CategoryOptionComboStore" />
    <property name="categoryOptionGroupStore" ref="org.hisp.dhis.category.CategoryOptionGroupStore" />
    <property name="categoryOptionGroupSetStore" ref="org.hisp.dhis.category.CategoryOptionGroupSetStore" />
    <property name="idObjectManager" ref="org.hisp.dhis.common.IdentifiableObjectManager" />
    <property name="currentUserService" ref="org.hisp.dhis.user.CurrentUserService" />
    <property name="aclService" ref="org.hisp.dhis.security.acl.AclService" />
  </bean>

  <bean id="org.hisp.dhis.organisationunit.OrganisationUnitService" class="org.hisp.dhis.organisationunit.DefaultOrganisationUnitService">
    <property name="organisationUnitStore" ref="org.hisp.dhis.organisationunit.OrganisationUnitStore" />
    <property name="dataSetService" ref="org.hisp.dhis.dataset.DataSetService" />
    <property name="organisationUnitLevelStore" ref="org.hisp.dhis.organisationunit.OrganisationUnitLevelStore" />
    <property name="currentUserService" ref="org.hisp.dhis.user.CurrentUserService" />
    <property name="versionService" ref="org.hisp.dhis.version.VersionService" />
    <property name="configurationService" ref="org.hisp.dhis.configuration.ConfigurationService" />
    <property name="userSettingService" ref="org.hisp.dhis.user.UserSettingService" />
    <property name="cacheProvider" ref="cacheProvider" />
  </bean>

  <bean id="org.hisp.dhis.organisationunit.OrganisationUnitGroupService"
    class="org.hisp.dhis.organisationunit.DefaultOrganisationUnitGroupService">
    <property name="organisationUnitGroupStore" ref="org.hisp.dhis.organisationunit.OrganisationUnitGroupStore" />
    <property name="organisationUnitGroupSetStore" ref="org.hisp.dhis.organisationunit.OrganisationUnitGroupSetStore" />
  </bean>

  <bean id="org.hisp.dhis.user.UserSettingService" class="org.hisp.dhis.user.DefaultUserSettingService">
    <property name="currentUserService" ref="org.hisp.dhis.user.CurrentUserService" />
    <property name="userSettingStore" ref="org.hisp.dhis.user.UserSettingStore" />
    <property name="userService" ref="org.hisp.dhis.user.UserService" />
    <property name="systemSettingManager" ref="org.hisp.dhis.setting.SystemSettingManager" />
  </bean>

  <bean id="org.hisp.dhis.user.UserService" class="org.hisp.dhis.user.DefaultUserService">
    <property name="userStore" ref="org.hisp.dhis.user.UserStore" />
    <property name="userGroupService" ref="org.hisp.dhis.user.UserGroupService" />
    <property name="userCredentialsStore" ref="org.hisp.dhis.user.UserCredentialsStore" />
    <property name="userAuthorityGroupStore" ref="org.hisp.dhis.user.UserAuthorityGroupStore" />
    <property name="currentUserService" ref="org.hisp.dhis.user.CurrentUserService" />
    <property name="systemSettingManager" ref="org.hisp.dhis.setting.SystemSettingManager" />
    <property name="passwordManager" ref="org.hisp.dhis.security.PasswordManager" />
  </bean>

  <bean id="org.hisp.dhis.user.UserGroupService" class="org.hisp.dhis.user.DefaultUserGroupService">
    <property name="userGroupStore" ref="org.hisp.dhis.user.UserGroupStore" />
    <property name="currentUserService" ref="org.hisp.dhis.user.CurrentUserService" />
    <property name="aclService" ref="org.hisp.dhis.security.acl.AclService" />
    <property name="cacheManager" ref="cacheManager" />
  </bean>

  <bean id="org.hisp.dhis.user.UserGroupAccessService" class="org.hisp.dhis.user.DefaultUserGroupAccessService">
    <property name="userGroupAccessStore" ref="org.hisp.dhis.user.UserGroupAccessStore" />
  </bean>

  <bean id="org.hisp.dhis.user.UserAccessService" class="org.hisp.dhis.user.DefaultUserAccessService">
    <property name="userAccessStore" ref="org.hisp.dhis.user.UserAccessStore" />
  </bean>

  <bean id="org.hisp.dhis.message.MessageService" class="org.hisp.dhis.message.DefaultMessageService">
    <property name="messageConversationStore" ref="org.hisp.dhis.message.MessageConversationStore" />
    <property name="currentUserService" ref="org.hisp.dhis.user.CurrentUserService" />
    <property name="configurationService" ref="org.hisp.dhis.configuration.ConfigurationService" />
    <property name="userSettingService" ref="org.hisp.dhis.user.UserSettingService" />
    <property name="i18nManager" ref="org.hisp.dhis.i18n.I18nManager" />
    <property name="systemSettingManager" ref="org.hisp.dhis.setting.SystemSettingManager" />
  </bean>

  <bean id="emailMessageSender" class="org.hisp.dhis.message.EmailMessageSender">
    <property name="systemSettingManager" ref="org.hisp.dhis.setting.SystemSettingManager" />
    <property name="userSettingService" ref="org.hisp.dhis.user.UserSettingService" />
  </bean>

  <bean id="org.hisp.dhis.email.EmailService" class="org.hisp.dhis.email.DefaultEmailService">
    <property name="emailMessageSender" ref="emailMessageSender" />
    <property name="currentUserService" ref="org.hisp.dhis.user.CurrentUserService" />
    <property name="systemSettingManager" ref="org.hisp.dhis.setting.SystemSettingManager" />
  </bean>

  <bean id="org.hisp.dhis.configuration.ConfigurationService" class="org.hisp.dhis.configuration.DefaultConfigurationService">
    <property name="configurationStore" ref="org.hisp.dhis.configuration.ConfigurationStore" />
  </bean>

  <bean id="org.hisp.dhis.constant.ConstantService" class="org.hisp.dhis.constant.DefaultConstantService">
    <property name="constantStore" ref="org.hisp.dhis.constant.ConstantStore" />
  </bean>

  <bean id="org.hisp.dhis.scheduling.JobInstance" class="org.hisp.dhis.scheduling.DefaultJobInstance" />

  <bean id="taskScheduler" class="org.springframework.scheduling.concurrent.ThreadPoolTaskScheduler">
    <property name="poolSize" value="25" />
  </bean>

  <bean id="org.hisp.dhis.scheduling.SchedulingManager" class="org.hisp.dhis.scheduling.DefaultSchedulingManager">
    <property name="taskScheduler" ref="taskScheduler" />
    <property name="taskExecutor" ref="taskScheduler" />
  </bean>

  <bean id="org.hisp.dhis.user.CurrentUserService" class="org.hisp.dhis.user.DefaultCurrentUserService" />

  <bean id="jobConfigurationService" class="org.hisp.dhis.scheduling.DefaultJobConfigurationService">
    <property name="jobConfigurationStore" ref="org.hisp.dhis.scheduling.JobConfigurationStore" />
  </bean>

  <bean id="mockJob" class="org.hisp.dhis.scheduling.MockJob" />

  <bean id="org.hisp.dhis.deletedobject.DeletedObjectService" class="org.hisp.dhis.deletedobject.DefaultDeletedObjectService" />

  <bean id="org.hisp.dhis.version.VersionService" class="org.hisp.dhis.version.DefaultVersionService">
    <property name="versionStore" ref="org.hisp.dhis.version.VersionStore" />
  </bean>

  <bean id="org.hisp.dhis.attribute.AttributeService" class="org.hisp.dhis.attribute.DefaultAttributeService">
    <property name="attributeStore" ref="org.hisp.dhis.attribute.AttributeStore" />
    <property name="attributeValueStore" ref="org.hisp.dhis.attribute.AttributeValueStore" />
  </bean>

  <bean id="org.hisp.dhis.option.OptionService" class="org.hisp.dhis.option.DefaultOptionService">
    <property name="optionSetStore" ref="org.hisp.dhis.option.OptionSetStore" />
    <property name="optionStore" ref="org.hisp.dhis.option.OptionStore" />
  </bean>

  <bean id="org.hisp.dhis.legend.LegendService" class="org.hisp.dhis.legend.DefaultLegendSetService">
    <property name="legendSetStore" ref="org.hisp.dhis.legend.LegendSetStore" />
  </bean>

  <bean id="org.hisp.dhis.dataset.notifications.DataSetNotificationService"
    class="org.hisp.dhis.dataset.notifications.DefaultDataSetNotificationService" />

  <bean id="org.hisp.dhis.dataset.notifications.DataSetNotificationTemplateService"
    class="org.hisp.dhis.dataset.notifications.DefaultDataSetNotificationTemplateService" />

  <bean id="org.hisp.dhis.dataset.notifications.DataSetNotificationEventPublisher"
    class="org.hisp.dhis.dataset.notifications.DataSetNotificationEventPublisher" />

  <bean id="org.hisp.dhis.dataset.notifications.DataSetNotificationEventListener"
    class="org.hisp.dhis.dataset.notifications.DataSetNotificationEventListener" />

  <bean id="dataSetNotificationJob" class="org.hisp.dhis.dataset.notifications.DataSetNotificationJob" />

  <bean id="org.hisp.dhis.security.oauth2.OAuth2ClientStore" class="org.hisp.dhis.security.oauth2.hibernate.HibernateOAuth2ClientStore">
    <property name="clazz" value="org.hisp.dhis.security.oauth2.OAuth2Client" />
    <property name="sessionFactory" ref="sessionFactory" />
    <property name="cacheable" value="true" />
  </bean>

  <bean id="oAuth2ClientService" class="org.hisp.dhis.security.oauth2.DefaultOAuth2ClientService" />

  <bean class="org.hisp.dhis.security.oauth2.OAuth2ClientDeletionHandler" />

  <bean id="org.hisp.dhis.setting.StyleManager" class="org.hisp.dhis.setting.DefaultStyleManager">
    <property name="systemSettingManager" ref="org.hisp.dhis.setting.SystemSettingManager" />
    <property name="userSettingService" ref="org.hisp.dhis.user.UserSettingService" />
    <property name="styles">
      <map>
        <entry>
          <key>
            <value>light_blue</value>
          </key>
          <value>light_blue/light_blue.css</value>
        </entry>
        <entry>
          <key>
            <value>green</value>
          </key>
          <value>green/green.css</value>
        </entry>
        <entry>
          <key>
            <value>myanmar</value>
          </key>
          <value>myanmar/myanmar.css</value>
        </entry>
        <entry>
          <key>
            <value>vietnam</value>
          </key>
          <value>vietnam/vietnam.css</value>
        </entry>
        <entry>
          <key>
            <value>india</value>
          </key>
          <value>india/india.css</value>
        </entry>
      </map>
    </property>
  </bean>

  <bean id="org.hisp.dhis.common.IdentifiableObjectManager" class="org.hisp.dhis.common.DefaultIdentifiableObjectManager" />

  <bean id="org.hisp.dhis.appmanager.AppManager" class="org.hisp.dhis.appmanager.DefaultAppManager" />

  <bean id="org.hisp.dhis.appmanager.LocalAppStorageService" class="org.hisp.dhis.appmanager.LocalAppStorageService" />

  <bean id="org.hisp.dhis.appmanager.JCloudsAppStorageService" class="org.hisp.dhis.appmanager.JCloudsAppStorageService">
    <property name="configurationProvider" ref="dhisConfigurationProvider" />
    <property name="locationManager" ref="locationManager" />
  </bean>

  <bean id="org.hisp.dhis.system.SystemService" class="org.hisp.dhis.system.DefaultSystemService" />

  <bean id="org.hisp.dhis.color.ColorService" class="org.hisp.dhis.color.DefaultColorService">
    <property name="colorSetStore" ref="org.hisp.dhis.color.ColorSetStore" />
  </bean>

  <bean id="org.hisp.dhis.icon.IconService" class="org.hisp.dhis.icon.DefaultIconService" />

  <bean id="org.hisp.dhis.analytics.AnalyticsTableHookService" class="org.hisp.dhis.analytics.DefaultAnalyticsTableHookService" />

  <!-- SMS Services -->

  <bean id="org.hisp.dhis.sms.MessageQueue" class="org.hisp.dhis.sms.DatabaseSupportedInternalMemoryMessageQueue" />

  <bean id="org.hisp.dhis.sms.config.SmsConfigurationManager" class="org.hisp.dhis.sms.config.DefaultSmsConfigurationManager" />

  <bean id="org.hisp.dhis.sms.incoming.SmsConsumerService" class="org.hisp.dhis.sms.incoming.DefaultSmsConsumerService" />

  <bean id="org.hisp.dhis.sms.SmsPublisher" class="org.hisp.dhis.sms.SmsPublisher" />

  <bean id="org.hisp.dhis.sms.SmsConsumerThread" class="org.hisp.dhis.sms.SmsConsumerThread" />

  <bean id="org.hisp.dhis.sms.incoming.IncomingSmsService" class="org.hisp.dhis.sms.incoming.DefaultIncomingSmsService">
    <property name="incomingSmsStore" ref="org.hisp.dhis.sms.hibernate.IncomingSmsStore" />
    <property name="incomingSmsQueue" ref="org.hisp.dhis.sms.MessageQueue" />
  </bean>

  <bean id="org.hisp.dhis.sms.outbound.OutboundSmsService" class="org.hisp.dhis.sms.outbound.DefaultOutboundSmsService">
    <property name="outboundSmsStore" ref="org.hisp.dhis.sms.hibernate.OutboundSmsStore" />
  </bean>

  <bean id="org.hisp.dhis.sms.config.GatewayAdministrationService"
    class="org.hisp.dhis.sms.config.DefaultGatewayAdministrationService" />

  <bean id="org.hisp.dhis.sms.config.BulkSmsGateway" class="org.hisp.dhis.sms.config.BulkSmsGateway" />

  <bean id="org.hisp.dhis.sms.config.ClickatellGateway" class="org.hisp.dhis.sms.config.ClickatellGateway" />

  <bean id="org.hisp.dhis.sms.config.SimplisticHttpGetGateWay" class="org.hisp.dhis.sms.config.SimplisticHttpGetGateWay" />

  <bean id="smsMessageSender" class="org.hisp.dhis.sms.config.SmsMessageSender" />

  <bean id="sendSmsJob" class="org.hisp.dhis.sms.job.SendSmsJob" scope="prototype" />

  <bean id="org.hisp.dhis.program.message.SmsDeliveryChannelStrategy" class="org.hisp.dhis.program.message.SmsDeliveryChannelStrategy" />

  <bean id="org.hisp.dhis.program.message.EmailDeliveryChannelStrategy"
    class="org.hisp.dhis.program.message.EmailDeliveryChannelStrategy" />


  <bean id="org.hisp.dhis.i18n.118nLocaleService" class="org.hisp.dhis.i18n.DefaultI18nLocaleService">
    <property name="localeStore" ref="org.hisp.dhis.i18n.I18nLocaleStore" />
  </bean>

  <!-- Tracker services -->

  <bean id="org.hisp.dhis.program.ProgramDataEntryService" class="org.hisp.dhis.program.DefaultProgramDataEntryService">
    <property name="dataElementService" ref="org.hisp.dhis.dataelement.DataElementService" />
    <property name="programStageInstanceService" ref="org.hisp.dhis.program.ProgramStageInstanceService" />
    <property name="programStageService" ref="org.hisp.dhis.program.ProgramStageService" />
    <property name="dataValueService" ref="org.hisp.dhis.trackedentitydatavalue.TrackedEntityDataValueService" />
  </bean>

  <bean id="org.hisp.dhis.program.ProgramExpressionService" class="org.hisp.dhis.program.DefaultProgramExpressionService">
    <property name="programExpressionStore" ref="org.hisp.dhis.program.ProgramExpressionStore" />
    <property name="programStageService" ref="org.hisp.dhis.program.ProgramStageService" />
    <property name="dataElementService" ref="org.hisp.dhis.dataelement.DataElementService" />
  </bean>

  <bean id="org.hisp.dhis.program.ProgramIndicatorService" class="org.hisp.dhis.program.DefaultProgramIndicatorService">
    <property name="programIndicatorStore" ref="org.hisp.dhis.program.ProgramIndicatorStore" />
    <property name="programStageService" ref="org.hisp.dhis.program.ProgramStageService" />
    <property name="dataElementService" ref="org.hisp.dhis.dataelement.DataElementService" />
    <property name="attributeService" ref="org.hisp.dhis.trackedentity.TrackedEntityAttributeService" />
    <property name="constantService" ref="org.hisp.dhis.constant.ConstantService" />
    <property name="statementBuilder" ref="statementBuilder" />
    <property name="programIndicatorGroupStore" ref="org.hisp.dhis.program.ProgramIndicatorGroupStore" />
  </bean>

  <bean id="org.hisp.dhis.relationship.RelationshipService" class="org.hisp.dhis.relationship.DefaultRelationshipService">
    <property name="relationshipStore" ref="org.hisp.dhis.relationship.RelationshipStore" />
  </bean>

  <bean id="org.hisp.dhis.relationship.RelationshipTypeService"
    class="org.hisp.dhis.relationship.DefaultRelationshipTypeService">
    <property name="relationshipTypeStore" ref="org.hisp.dhis.relationship.RelationshipTypeStore" />
  </bean>

  <bean id="org.hisp.dhis.program.ProgramStageInstanceService"
    class="org.hisp.dhis.program.DefaultProgramStageInstanceService">
    <property name="programStageInstanceStore" ref="org.hisp.dhis.program.ProgramStageInstanceStore" />
    <property name="programInstanceService" ref="org.hisp.dhis.program.ProgramInstanceService" />
    <property name="currentUserService" ref="org.hisp.dhis.user.CurrentUserService" />
  </bean>

  <bean id="org.hisp.dhis.program.ProgramInstanceService" class="org.hisp.dhis.program.DefaultProgramInstanceService" />

  <bean id="org.hisp.dhis.program.ProgramStageService" class="org.hisp.dhis.program.DefaultProgramStageService">
    <property name="programStageStore" ref="org.hisp.dhis.program.ProgramStageStore" />
  </bean>

  <bean id="org.hisp.dhis.program.notification.ProgramNotificationService"
    class="org.hisp.dhis.program.notification.DefaultProgramNotificationService">
    <property name="programMessageService" ref="org.hisp.dhis.program.message.ProgramMessageService" />
    <property name="messageService" ref="org.hisp.dhis.message.MessageService" />
    <property name="programInstanceStore" ref="org.hisp.dhis.program.ProgramInstanceStore" />
    <property name="programStageInstanceStore" ref="org.hisp.dhis.program.ProgramStageInstanceStore" />
    <property name="identifiableObjectManager" ref="org.hisp.dhis.common.IdentifiableObjectManager" />
    <property name="programNotificationRenderer" ref="programNotificationMessageRenderer" />
    <property name="programStageNotificationRenderer" ref="programStageNotificationMessageRenderer" />
    <property name="programNotificationStore" ref="org.hisp.dhis.program.notification.ProgramNotificationTemplateStore" />
  </bean>

  <bean id="org.hisp.dhis.program.notification.ProgramNotificationPublisher"
    class="org.hisp.dhis.program.notification.ProgramNotificationPublisher" />

  <bean id="org.hisp.dhis.program.notification.ProgramNotificationListener"
    class="org.hisp.dhis.program.notification.ProgramNotificationListener" />

  <bean id="org.hisp.dhis.program.ProgramStageSectionService" class="org.hisp.dhis.program.DefaultProgramStageSectionService">
    <property name="programStageSectionStore" ref="org.hisp.dhis.program.ProgramStageSectionStore" />
  </bean>

  <bean id="org.hisp.dhis.program.ProgramService" class="org.hisp.dhis.program.DefaultProgramService">
    <property name="programStore" ref="org.hisp.dhis.program.ProgramStore" />
    <property name="currentUserService" ref="org.hisp.dhis.user.CurrentUserService" />
    <property name="organisationUnitService" ref="org.hisp.dhis.organisationunit.OrganisationUnitService" />
  </bean>

  <bean id="org.hisp.dhis.program.ProgramTrackedEntityAttributeGroupService"
    class="org.hisp.dhis.program.DefaultProgramTrackedEntityAttributeGroupService">
    <property name="attributeGroupStore" ref="org.hisp.dhis.program.ProgramTrackedEntityAttributeGroupStore" />
  </bean>

  <bean id="org.hisp.dhis.textpattern.TextPatternService" class="org.hisp.dhis.textpattern.DefaultTextPatternService" />

  <bean id="org.hisp.dhis.reservedvalue.ReservedValueService" class="org.hisp.dhis.reservedvalue.DefaultReservedValueService">
  </bean>

  <!-- Outbound messaging services -->

  <bean id="org.hisp.dhis.outboundmessage.OutboundMessageService"
    class="org.hisp.dhis.outboundmessage.DefaultOutboundMessageBatchService">
    <property name="messageSenders">
      <map>
        <entry key="SMS" value-ref="smsMessageSender" />
        <entry key="EMAIL" value-ref="emailMessageSender" />
      </map>
    </property>
  </bean>

  <!-- ProgramMessage services -->

  <bean id="org.hisp.dhis.program.message.ProgramMessageService" class="org.hisp.dhis.program.message.DefaultProgramMessageService">
  </bean>

  <bean id="org.hisp.dhis.sms.SmsMessageBatchCreatorService" class="org.hisp.dhis.sms.SmsMessageBatchCreatorService">
  </bean>

  <bean id="org.hisp.dhis.email.EmailMessageBatchCreator" class="org.hisp.dhis.email.EmailMessageBatchCreatorService">
  </bean>

  <bean id="org.hisp.dhis.trackedentity.TrackedEntityInstanceService"
    class="org.hisp.dhis.trackedentity.DefaultTrackedEntityInstanceService" />

  <bean id="org.hisp.dhis.trackedentity.TrackedEntityProgramOwnerService"
    class="org.hisp.dhis.trackedentity.DefaultTrackedEntityProgramOwnerService" />

  <bean id="org.hisp.dhis.trackedentity.TrackerOwnershipManager"
    class="org.hisp.dhis.trackedentity.DefaultTrackerOwnershipManager">
  </bean>

  <bean id="org.hisp.dhis.trackedentityfilter.TrackedEntityInstanceFilterService"
    class="org.hisp.dhis.trackedentityfilter.DefaultTrackedEntityInstanceFilterService">
    <property name="trackedEntityInstanceFilterStore" ref="org.hisp.dhis.trackedentityfilter.TrackedEntityInstanceFilterStore" />
  </bean>

  <bean id="org.hisp.dhis.trackedentity.TrackedEntityAttributeService"
    class="org.hisp.dhis.trackedentity.DefaultTrackedEntityAttributeService" />

  <bean id="org.hisp.dhis.trackedentityattributevalue.TrackedEntityAttributeValueService"
    class="org.hisp.dhis.trackedentityattributevalue.DefaultTrackedEntityAttributeValueService">
    <property name="attributeValueStore" ref="org.hisp.dhis.trackedentityattributevalue.TrackedEntityAttributeValueStore" />
  </bean>

  <bean id="org.hisp.dhis.trackedentitydatavalue.TrackedEntityDataValueService"
    class="org.hisp.dhis.trackedentitydatavalue.DefaultTrackedEntityDataValueService">
  </bean>

  <bean id="org.hisp.dhis.program.ProgramStageDataElementService"
    class="org.hisp.dhis.program.DefaultProgramStageDataElementService">
    <property name="programStageDataElementStore" ref="org.hisp.dhis.program.ProgramStageDataElementStore" />
  </bean>

  <bean id="org.hisp.dhis.trackedentity.TrackedEntityTypeService" class="org.hisp.dhis.trackedentity.DefaultTrackedEntityTypeService">
    <property name="trackedEntityTypeStore" ref="org.hisp.dhis.trackedentity.TrackedEntityTypeStore" />
  </bean>

  <bean id="org.hisp.dhis.trackedentitycomment.TrackedEntityCommentService"
    class="org.hisp.dhis.trackedentitycomment.DefaultTrackedEntityCommentService">
    <property name="commentStore" ref="org.hisp.dhis.trackedentitycomment.TrackedEntityCommentStore" />
  </bean>

  <bean id="org.hisp.dhis.predictor.PredictorService" class="org.hisp.dhis.predictor.DefaultPredictorService">
    <property name="predictorGroupStore" ref="org.hisp.dhis.predictor.PredictorGroupStore" />
  </bean>

  <bean id="org.hisp.dhis.trackedentitycomment.TrackedEntityCommentStore"
    class="org.hisp.dhis.trackedentitycomment.hibernate.HibernateTrackedEntityCommentStore">
    <property name="clazz" value="org.hisp.dhis.trackedentitycomment.TrackedEntityComment" />
    <property name="sessionFactory" ref="sessionFactory" />
    <property name="jdbcTemplate" ref="jdbcTemplate" />
  </bean>

  <bean id="org.hisp.dhis.program.notification.ProgramNotificationStore"
    class="org.hisp.dhis.common.hibernate.HibernateIdentifiableObjectStore">
    <property name="clazz" value="org.hisp.dhis.program.notification.ProgramNotificationTemplate" />
    <property name="sessionFactory" ref="sessionFactory" />
    <property name="cacheable" value="true" />
  </bean>

  <bean id="org.hisp.dhis.program.notification.ProgramNotificationInstanceStore"
    class="org.hisp.dhis.common.hibernate.HibernateIdentifiableObjectStore">
    <property name="clazz" value="org.hisp.dhis.program.notification.ProgramNotificationInstance" />
    <property name="sessionFactory" ref="sessionFactory" />
    <property name="cacheable" value="true" />
  </bean>

  <bean id="org.hisp.dhis.program.notification.ProgramNotificationTemplateStore"
    class="org.hisp.dhis.program.notification.DefaultProgramNotificationTemplateStore">
    <property name="clazz" value="org.hisp.dhis.program.notification.ProgramNotificationTemplate" />
    <property name="sessionFactory" ref="sessionFactory" />
    <property name="cacheable" value="true" />
  </bean>

  <bean id="org.hisp.dhis.eventreport.EventReportService" class="org.hisp.dhis.eventreport.DefaultEventReportService">
    <property name="eventReportStore" ref="org.hisp.dhis.eventreport.EventReportStore" />
  </bean>

  <bean id="org.hisp.dhis.eventchart.EventChartService" class="org.hisp.dhis.eventchart.DefaultEventChartService">
    <property name="eventChartStore" ref="org.hisp.dhis.eventchart.EventChartStore" />
  </bean>

  <bean id="org.hisp.dhis.keyjsonvalue.KeyJsonValueService" class="org.hisp.dhis.keyjsonvalue.DefaultKeyJsonValueService">
    <property name="keyJsonValueStore" ref="org.hisp.dhis.keyjsonvalue.KeyJsonValueStore" />
  </bean>

  <bean id="org.hisp.dhis.userkeyjsonvalue.UserKeyJsonValueService" class="org.hisp.dhis.userkeyjsonvalue.DefaultUserKeyJsonValueService">
    <property name="userKeyJsonValueStore" ref="org.hisp.dhis.userkeyjsonvalue.UserKeyJsonValueStore" />
  </bean>

  <!-- SMS services -->

  <bean id="org.hisp.dhis.sms.command.SMSCommandService" class="org.hisp.dhis.sms.command.DefaultSMSCommandService">
    <property name="smsCommandStore" ref="org.hisp.dhis.sms.command.hibernate.SMSCommandStore" />
  </bean>

  <bean id="org.hisp.dhis.sms.listener.DataValueSMSListener" class="org.hisp.dhis.sms.listener.DataValueSMSListener" />

  <bean id="org.hisp.dhis.sms.listener.J2MEDataValueSMSListener"
    class="org.hisp.dhis.sms.listener.J2MEDataValueSMSListener" />

  <bean id="org.hisp.dhis.sms.listener.UnregisteredSMSListener"
    class="org.hisp.dhis.sms.listener.UnregisteredSMSListener" />

  <bean id="org.hisp.dhis.sms.listener.DhisMessageAlertListener"
    class="org.hisp.dhis.sms.listener.DhisMessageAlertListener" />

  <bean id="org.hisp.dhis.sms.listener.TrackedEntityRegistrationSMSListener"
    class="org.hisp.dhis.sms.listener.TrackedEntityRegistrationSMSListener" />


  <bean id="org.hisp.dhis.sms.listener.ProgramStageDataEntrySMSListener"
    class="org.hisp.dhis.sms.listener.ProgramStageDataEntrySMSListener" />

  <bean id="org.hisp.dhis.sms.listener.SingleEventListener" class="org.hisp.dhis.sms.listener.SingleEventListener" />

  <!-- Notification renderers -->

  <bean id="programNotificationMessageRenderer" class="org.hisp.dhis.notification.ProgramNotificationMessageRenderer" />

  <bean id="programStageNotificationMessageRenderer" class="org.hisp.dhis.notification.ProgramStageNotificationMessageRenderer" />

  <bean id="dataSetNotificationMessageRenderer" class="org.hisp.dhis.notification.DataSetNotificationMessageRenderer" />

  <!-- Notification loggin -->

  <bean id="org.hisp.dhis.notification.logging.NotificationLoggingStore"
    class="org.hisp.dhis.notification.logging.HibernateNotificationLoggingStore">
    <property name="clazz" value="org.hisp.dhis.notification.logging.ExternalNotificationLogEntry" />
    <property name="jdbcTemplate" ref="jdbcTemplate" />
    <property name="sessionFactory" ref="sessionFactory" />
    <property name="cacheable" value="true" />
  </bean>

  <bean id="org.hisp.dhis.notification.logging.NotificationLoggingService"
    class="org.hisp.dhis.notification.logging.DefaultNotificationLoggingService" />

  <!-- I18n UI -->

  <bean id="org.hisp.dhis.i18n.locale.LocaleManager" class="org.hisp.dhis.i18n.ui.locale.UserSettingLocaleManager">
    <property name="userSettingService" ref="org.hisp.dhis.user.UserSettingService" />
    <property name="resourceBundleManager" ref="org.hisp.dhis.i18n.ui.resourcebundle.ResourceBundleManager" />
  </bean>

  <bean id="org.hisp.dhis.i18n.I18nManager" class="org.hisp.dhis.i18n.ui.DefaultI18nManager">
    <property name="resourceBundleManager" ref="org.hisp.dhis.i18n.ui.resourcebundle.ResourceBundleManager" />
    <property name="localeManager" ref="org.hisp.dhis.i18n.locale.LocaleManager" />
  </bean>

  <bean id="org.hisp.dhis.i18n.ui.resourcebundle.ResourceBundleManager"
    class="org.hisp.dhis.i18n.ui.resourcebundle.DefaultResourceBundleManager">
    <property name="globalResourceBundleName" value="i18n_global" />
    <property name="specificResourceBundleName" value="i18n_module" />
  </bean>

  <!-- Scheduled jobs -->

  <bean id="programNotificationsJob"
    class="org.hisp.dhis.program.notification.ProgramNotificationJob" />

  <bean id="removeExpiredReservedValuesJob" class="org.hisp.dhis.reservedvalue.RemoveExpiredReservedValuesJob" />

  <!-- Startup routine definitions -->
  
  <bean id="org.hisp.dhis.period.PeriodTypePopulator" class="org.hisp.dhis.period.PeriodTypePopulator">
    <property name="periodStore" ref="org.hisp.dhis.period.PeriodStore" />
    <property name="name" value="PeriodTypePopulator" />
    <property name="runlevel" value="2" />
  </bean>

  <bean id="twoFAPopulator" class="org.hisp.dhis.startup.TwoFAPopulator">
    <property name="userService" ref="org.hisp.dhis.user.UserService" />
    <property name="currentUserService" ref="org.hisp.dhis.user.CurrentUserService" />
    <property name="runlevel" value="2" />
    <property name="skipInTests" value="true" />
  </bean>

  <bean id="schedulerStart" class="org.hisp.dhis.startup.SchedulerStart">
    <property name="jobConfigurationService" ref="jobConfigurationService" />
    <property name="schedulingManager" ref="org.hisp.dhis.scheduling.SchedulingManager" />
    <property name="messageService" ref="org.hisp.dhis.message.MessageService" />
    <property name="runlevel" value="14" />
    <property name="skipInTests" value="true" />
    <property name="redisEnabled" ref="redisEnabled" />
    <property name="leaderElectionTime" ref="leaderElectionTime" />
  </bean>

  <bean id="redisEnabled" class="org.hisp.dhis.external.conf.ConfigurationPropertyFactoryBean">
    <constructor-arg value="REDIS_ENABLED" />
  </bean>

  <bean id="leaderElectionTime" class="org.hisp.dhis.external.conf.ConfigurationPropertyFactoryBean">
    <constructor-arg value="LEADER_TIME_TO_LIVE" />
  </bean>

  <bean id="org.hisp.dhis.dataelement.DataElementDefaultDimensionPopulator"
    class="org.hisp.dhis.dataelement.DataElementDefaultDimensionPopulator">
    <property name="dataElementService" ref="org.hisp.dhis.dataelement.DataElementService" />
    <property name="categoryService" ref="org.hisp.dhis.category.CategoryService" />
    <property name="name" value="DataElementDefaultDimensionPopulator" />
    <property name="runlevel" value="3" />
  </bean>

  <bean id="org.hisp.dhis.startup.ModelUpgrader" class="org.hisp.dhis.startup.ModelUpgrader">
    <property name="name" value="ModelUpgrader" />
    <property name="runlevel" value="7" />
    <property name="skipInTests" value="true" />
  </bean>

  <bean id="org.hisp.dhis.startup.FavoriteDataItemUpgrader" class="org.hisp.dhis.startup.FavoriteDataItemUpgrader">
    <property name="name" value="FavoriteDataItemUpgrader" />
    <property name="runlevel" value="9" />
    <property name="skipInTests" value="true" />
    <property name="jdbcTemplate" ref="jdbcTemplate" />
  </bean>

  <bean id="org.hisp.dhis.startup.AnalyticalObjectEmbeddedDimensionUpgrader"
    class="org.hisp.dhis.startup.AnalyticalObjectEmbeddedDimensionUpgrader">
    <property name="runlevel" value="9" />
    <property name="skipInTests" value="true" />
  </bean>

  <bean id="org.hisp.dhis.startup.ExpressionUpgrader" class="org.hisp.dhis.startup.ExpressionUpgrader">
    <property name="name" value="ExpressionUpgrader" />
    <property name="runlevel" value="11" />
    <property name="skipInTests" value="true" />
  </bean>

  <bean id="org.hisp.dhis.startup.ConfigurationPopulator" class="org.hisp.dhis.startup.ConfigurationPopulator">
    <property name="name" value="ConfigurationPopulator" />
    <property name="runlevel" value="12" />
    <property name="skipInTests" value="true" />
  </bean>

  <bean id="org.hisp.dhis.startup.I18nLocalePopulator" class="org.hisp.dhis.startup.I18nLocalePopulator">
    <property name="name" value="I18nLocalePopulator" />
    <property name="runlevel" value="13" />
    <property name="skipInTests" value="true" />
  </bean>

  <bean id="org.hisp.dhis.startup.SettingUpgrader" class="org.hisp.dhis.startup.SettingUpgrader">
    <property name="name" value="SettingUpgrader" />
    <property name="runlevel" value="14" />
    <property name="skipInTests" value="true" />
  </bean>

  <!-- DeletionHandlers -->

  <bean id="org.hisp.dhis.dataapproval.DataApprovalDeletionHandler" class="org.hisp.dhis.dataapproval.DataApprovalDeletionHandler">
    <property name="jdbcTemplate" ref="jdbcTemplate" />
  </bean>

  <bean id="org.hisp.dhis.dataelement.DataElementDeletionHandler" class="org.hisp.dhis.dataelement.DataElementDeletionHandler">
    <property name="jdbcTemplate" ref="jdbcTemplate" />
  </bean>

  <bean id="org.hisp.dhis.dataelement.DataElementOperandDeletionHandler"
    class="org.hisp.dhis.dataelement.DataElementOperandDeletionHandler">
    <property name="jdbcTemplate" ref="jdbcTemplate" />
  </bean>

  <bean id="org.hisp.dhis.dataelement.DataElementGroupDeletionHandler" class="org.hisp.dhis.dataelement.DataElementGroupDeletionHandler" />

  <bean id="org.hisp.dhis.category.CategoryOptionDeletionHandler"
    class="org.hisp.dhis.category.CategoryOptionDeletionHandler" />

  <bean id="org.hisp.dhis.category.CategoryOptionComboDeletionHandler"
    class="org.hisp.dhis.category.CategoryOptionComboDeletionHandler">
    <property name="jdbcTemplate" ref="jdbcTemplate" />
    <property name="categoryService" ref="org.hisp.dhis.category.CategoryService" />
  </bean>

  <bean id="org.hisp.dhis.category.CategoryComboDeletionHandler"
    class="org.hisp.dhis.category.CategoryComboDeletionHandler">
    <property name="categoryService" ref="org.hisp.dhis.category.CategoryService" />
  </bean>

  <bean id="org.hisp.dhis.category.CategoryDimensionDeletionHandler"
    class="org.hisp.dhis.category.CategoryDimensionDeletionHandler">
    <property name="jdbcTemplate" ref="jdbcTemplate" />
  </bean>

  <bean id="org.hisp.dhis.dataset.DataSetDeletionHandler" class="org.hisp.dhis.dataset.DataSetDeletionHandler" />

  <bean id="org.hisp.dhis.dataset.CompleteDataSetRegistrationDeletionHandler"
    class="org.hisp.dhis.dataset.CompleteDataSetRegistrationDeletionHandler">
    <property name="completeDataSetRegistrationService" ref="org.hisp.dhis.dataset.CompleteDataSetRegistrationService" />
    <property name="jdbcTemplate" ref="jdbcTemplate" />
  </bean>

  <bean id="org.hisp.dhis.dataset.SectionDeletionHandler" class="org.hisp.dhis.dataset.SectionDeletionHandler">
    <property name="sectionService" ref="org.hisp.dhis.dataset.SectionService" />
  </bean>

  <bean id="org.hisp.dhis.indicator.IndicatorDeletionHandler" class="org.hisp.dhis.indicator.IndicatorDeletionHandler">
    <property name="indicatorService" ref="org.hisp.dhis.indicator.IndicatorService" />
    <property name="expressionService" ref="org.hisp.dhis.expression.ExpressionService" />
  </bean>

  <bean id="org.hisp.dhis.indicator.IndicatorGroupDeletionHandler" class="org.hisp.dhis.indicator.IndicatorGroupDeletionHandler" />

  <bean id="org.hisp.dhis.indicator.IndicatorGroupSetDeletionHandler" class="org.hisp.dhis.indicator.IndicatorGroupSetDeletionHandler" />

  <bean id="org.hisp.dhis.datavalue.DataValueDeletionHandler" class="org.hisp.dhis.datavalue.DataValueDeletionHandler">
    <property name="jdbcTemplate" ref="jdbcTemplate" />
  </bean>

  <bean id="org.hisp.dhis.dimension.DataDimensionItemDeletionHandler" class="org.hisp.dhis.dimension.DataDimensionItemDeletionHandler">
    <property name="jdbcTemplate" ref="jdbcTemplate" />
  </bean>

  <bean id="org.hisp.dhis.dataset.DataInputPeriodDeletionHandler" class="org.hisp.dhis.dataset.DataInputPeriodDeletionHandler">
    <property name="jdbcTemplate" ref="jdbcTemplate" />
  </bean>

  <bean id="org.hisp.dhis.datavalue.DataValueAuditDeletionHandler" class="org.hisp.dhis.datavalue.DataValueAuditDeletionHandler">
    <property name="jdbcTemplate" ref="jdbcTemplate" />
  </bean>

  <bean id="org.hisp.dhis.organisationunit.OrganisationUnitDeletionHandler"
    class="org.hisp.dhis.organisationunit.OrganisationUnitDeletionHandler" />

  <bean id="org.hisp.dhis.organisationunit.OrganisationUnitGroupDeletionHandler"
    class="org.hisp.dhis.organisationunit.OrganisationUnitGroupDeletionHandler" />

  <bean id="org.hisp.dhis.organisationunit.OrganisationUnitGroupSetDeletionHandler"
    class="org.hisp.dhis.organisationunit.OrganisationUnitGroupSetDeletionHandler" />

  <bean id="org.hisp.dhis.predictor.PredictorDeletionHandler"
    class="org.hisp.dhis.predictor.PredictorDeletionHandler" />

  <bean id="org.hisp.dhis.predictor.PredictorGroupDeletionHandler"
    class="org.hisp.dhis.predictor.PredictorGroupDeletionHandler" />

  <bean id="org.hisp.dhis.user.UserCredentialsDeletionHandler" class="org.hisp.dhis.user.UserCredentialsDeletionHandler" />

  <bean id="org.hisp.dhis.user.UserDeletionHandler" class="org.hisp.dhis.user.UserDeletionHandler" />

  <bean id="org.hisp.dhis.user.UserGroupDeletionHandler" class="org.hisp.dhis.user.UserGroupDeletionHandler">
    <property name="jdbcTemplate" ref="jdbcTemplate" />
  </bean>

  <bean id="org.hisp.dhis.user.UserAuthorityGroupDeletionHandler" class="org.hisp.dhis.user.UserAuthorityGroupDeletionHandler">
    <property name="userService" ref="org.hisp.dhis.user.UserService" />
  </bean>

  <bean id="org.hisp.dhis.user.UserSettingDeletionHandler" class="org.hisp.dhis.user.UserSettingDeletionHandler" />

  <bean id="org.hisp.dhis.category.CategoryDeletionHandler"
    class="org.hisp.dhis.category.CategoryDeletionHandler" />

  <bean id="org.hisp.dhis.dataelement.DataElementGroupSetDeletionHandler"
    class="org.hisp.dhis.dataelement.DataElementGroupSetDeletionHandler" />

  <bean id="org.hisp.dhis.configuration.ConfigurationDeletionHandler" class="org.hisp.dhis.configuration.ConfigurationDeletionHandler" />

  <bean id="org.hisp.dhis.message.MessageConversationDeletionHandler" class="org.hisp.dhis.message.MessageConversationDeletionHandler">
    <property name="messageService" ref="org.hisp.dhis.message.MessageService" />
  </bean>

  <bean id="org.hisp.dhis.attribute.AttributeValueDeletionHandler" class="org.hisp.dhis.attribute.AttributeValueDeletionHandler">
    <property name="attributeService" ref="org.hisp.dhis.attribute.AttributeService" />
    <property name="jdbcTemplate" ref="jdbcTemplate" />
  </bean>

  <bean id="org.hisp.dhis.legend.LegendSetDeletionHandler" class="org.hisp.dhis.legend.LegendSetDeletionHandler" />

  <bean id="org.hisp.dhis.category.CategoryOptionGroupDeletionHandler"
    class="org.hisp.dhis.category.CategoryOptionGroupDeletionHandler" />

  <bean id="org.hisp.dhis.category.CategoryOptionGroupSetDeletionHandler"
    class="org.hisp.dhis.category.CategoryOptionGroupSetDeletionHandler" />

  <bean id="org.hisp.dhis.program.ProgramInstanceDeletionHandler"
    class="org.hisp.dhis.program.ProgramInstanceDeletionHandler">
    <property name="programInstanceService" ref="org.hisp.dhis.program.ProgramInstanceService" />
  </bean>

  <bean id="org.hisp.dhis.program.ProgramIndicatorGroupDeletionHandler"
    class="org.hisp.dhis.program.ProgramIndicatorGroupDeletionHandler">
  </bean>

  <bean id="org.hisp.dhis.relationship.RelationshipDeletionHandler"
    class="org.hisp.dhis.relationship.RelationshipDeletionHandler">
    <property name="relationshipSevice" ref="org.hisp.dhis.relationship.RelationshipService" />
  </bean>

  <bean id="org.hisp.dhis.trackedentityattributevalue.TrackedEntityAttributeValueDeletionHandler"
    class="org.hisp.dhis.trackedentityattributevalue.TrackedEntityAttributeValueDeletionHandler">
    <property name="attributeValueService" ref="org.hisp.dhis.trackedentityattributevalue.TrackedEntityAttributeValueService" />
  </bean>

  <bean id="org.hisp.dhis.program.ProgramDeletionHandler" class="org.hisp.dhis.program.ProgramDeletionHandler" />

  <bean id="org.hisp.dhis.trackedentity.TrackedEntityInstanceDeletionHandler"
    class="org.hisp.dhis.trackedentity.TrackedEntityInstanceDeletionHandler">
    <property name="jdbcTemplate" ref="jdbcTemplate" />
  </bean>

  <bean class="org.hisp.dhis.trackedentity.TrackedEntityDataElementDimensionDeletionHandler" />

  <bean id="org.hisp.dhis.program.ProgramStageDataElementDeletionHandler"
    class="org.hisp.dhis.program.ProgramStageDataElementDeletionHandler">
  </bean>

  <bean id="org.hisp.dhis.program.ProgramStageDeletionHandler"
    class="org.hisp.dhis.program.ProgramStageDeletionHandler">
    <property name="programStageService" ref="org.hisp.dhis.program.ProgramStageService" />
    <property name="jdbcTemplate" ref="jdbcTemplate" />
  </bean>

  <bean id="org.hisp.dhis.trackedentitydatavalue.TrackedEntityDataValueDeletionHandler"
    class="org.hisp.dhis.trackedentitydatavalue.TrackedEntityDataValueDeletionHandler">
    <property name="jdbcTemplate" ref="jdbcTemplate" />
  </bean>

  <bean id="org.hisp.dhis.program.ProgramDataEntryFormDeletionHandler"
    class="org.hisp.dhis.program.ProgramDataEntryFormDeletionHandler">
    <property name="dataEntryFormService" ref="org.hisp.dhis.dataentryform.DataEntryFormService" />
    <property name="programStageService" ref="org.hisp.dhis.program.ProgramStageService" />
  </bean>

  <bean id="org.hisp.dhis.program.ProgramStageInstanceDeletionHandler"
    class="org.hisp.dhis.program.ProgramStageInstanceDeletionHandler">
    <property name="jdbcTemplate" ref="jdbcTemplate" />
  </bean>

  <bean id="org.hisp.dhis.program.ProgramStageSectionDeletionHandler"
    class="org.hisp.dhis.program.ProgramStageSectionDeletionHandler">
  </bean>

  <bean id="org.hisp.dhis.program.ProgramIndicatorDeletionHandler"
    class="org.hisp.dhis.program.ProgramIndicatorDeletionHandler" />

  <bean id="org.hisp.dhis.eventchart.EventChartDeletionHandler"
    class="org.hisp.dhis.eventchart.EventChartDeletionHandler" />

  <bean id="org.hisp.dhis.eventreport.EventReportDeletionHandler"
    class="org.hisp.dhis.eventreport.EventReportDeletionHandler" />

  <bean id="org.hisp.dhis.sms.command.SMSCommandDeletionHandler"
    class="org.hisp.dhis.sms.command.SMSCommandDeletionHandler" />

  <bean id="org.hisp.dhis.sms.command.code.SMSCodesDeletionHandler"
    class="org.hisp.dhis.sms.command.code.SMSCodesDeletionHandler">
    <property name="jdbcTemplate" ref="jdbcTemplate" />
  </bean>

  <bean id="org.hisp.dhis.reservedvalue.ReservedValueDeletionHandler"
    class="org.hisp.dhis.reservedvalue.ReservedValueDeletionHandler" />

  <bean id="org.hisp.dhis.reservedvalue.SequentialNumberCounterDeletionHandler"
    class="org.hisp.dhis.reservedvalue.SequentialNumberCounterDeletionHandler">
    <constructor-arg ref="org.hisp.dhis.reservedvalue.SequentialNumberCounterStore" />
  </bean>

  <bean id="org.hisp.dhis.fileresource.ExternalFileResourceDeletionHandler"
        class="org.hisp.dhis.fileresource.ExternalFileResourceDeletionHandler">
    <property name="jdbcTemplate" ref="jdbcTemplate" />
  </bean>

  <bean id="org.hisp.dhis.fileresource.MessageAttachmentDeletionHandler"
        class="org.hisp.dhis.fileresource.MessageAttachmentDeletionHandler">
    <property name="jdbcTemplate" ref="jdbcTemplate" />
  </bean>

  <bean id="sessionRegistry" class="org.springframework.security.core.session.SessionRegistryImpl" />

  <!-- AOP definitions -->

  <aop:config>
    <aop:aspect ref="deletionInterceptor">
      <aop:before pointcut="execution( * org.hisp.dhis.common.IdentifiableObjectManager.delete*(..) )" method="intercept" />
      <aop:before pointcut="execution( * org.hisp.dhis.dataapproval.DataApprovalLevelService.delete*(..) )" method="intercept" />
      <aop:before pointcut="execution( * org.hisp.dhis.dataelement.DataElementService.delete*(..) )" method="intercept" />
      <aop:before pointcut="execution( * org.hisp.dhis.category.CategoryService.delete*(..) )" method="intercept" />
      <aop:before pointcut="execution( * org.hisp.dhis.dataset.DataSetService.deleteDataSet(..) )" method="intercept" />
      <aop:before pointcut="execution( * org.hisp.dhis.dataset.SectionService.delete*(..) )" method="intercept" />
      <aop:before pointcut="execution( * org.hisp.dhis.indicator.IndicatorService.delete*(..) )" method="intercept" />
      <aop:before pointcut="execution( * org.hisp.dhis.expression.ExpressionService.delete*(..) )" method="intercept" />
      <aop:before pointcut="execution( * org.hisp.dhis.period.PeriodService.delete*(..) )" method="intercept" />
      <aop:before pointcut="execution( * org.hisp.dhis.organisationunit.OrganisationUnitService.delete*(..) )" method="intercept" />
      <aop:before pointcut="execution( * org.hisp.dhis.organisationunit.OrganisationUnitGroupService.delete*(..) )" method="intercept" />
      <aop:before pointcut="execution( * org.hisp.dhis.predictor.PredictorService.delete*(..) )" method="intercept" />
      <aop:before pointcut="execution( * org.hisp.dhis.user.UserService.delete*(..) )" method="intercept" />
      <aop:before pointcut="execution( * org.hisp.dhis.user.UserGroupService.delete*(..) )" method="intercept" />
      <aop:before pointcut="execution( * org.hisp.dhis.option.OptionService.delete*(..) )" method="intercept" />
      <aop:before pointcut="execution( * org.hisp.dhis.attribute.AttributeService.delete*(..) )" method="intercept" />
      <aop:before pointcut="execution( * org.hisp.dhis.legend.LegendSetService.deleteLegend(..) )" method="intercept" />
      <aop:before pointcut="execution( * org.hisp.dhis.legend.LegendSetService.deleteLegendSet(..) )" method="intercept" />
      <aop:before pointcut="execution( * org.hisp.dhis.mapping.MappingService.deleteMapView(..) )" method="intercept" />
      <aop:before pointcut="execution( * org.hisp.dhis.mapping.MappingService.deleteMap(..) )" method="intercept" />
      <aop:before pointcut="execution( * org.hisp.dhis.i18n.I18nLocaleService.delete*(..) )" method="intercept" />
      <aop:before pointcut="execution( * org.hisp.dhis.trackedentity.TrackedEntityTypeService.delete*(..) )" method="intercept" />
      <aop:before pointcut="execution( * org.hisp.dhis.trackedentity.TrackedEntityInstanceService.delete*(..) )" method="intercept" />
      <aop:before pointcut="execution( * org.hisp.dhis.trackedentityattributevalue.TrackedEntityAttributeValueService.delete*(..) )"
        method="intercept" />
      <aop:before pointcut="execution( * org.hisp.dhis.trackedentity.TrackedEntityAttributeService.delete*(..) )" method="intercept" />
      <aop:before pointcut="execution( * org.hisp.dhis.relationship.RelationshipService.delete*(..) )" method="intercept" />
      <aop:before pointcut="execution( * org.hisp.dhis.relationship.RelationshipTypeService.delete*(..) )" method="intercept" />
      <aop:before pointcut="execution( * org.hisp.dhis.program.ProgramService.delete*(..) )" method="intercept" />
      <aop:before pointcut="execution( * org.hisp.dhis.program.ProgramStageSectionService.delete*(..) )" method="intercept" />
      <aop:before pointcut="execution( * org.hisp.dhis.program.ProgramInstanceService.delete*(..) )" method="intercept" />
      <aop:before pointcut="execution( * org.hisp.dhis.program.ProgramStageService.delete*(..) )" method="intercept" />
      <aop:before pointcut="execution( * org.hisp.dhis.program.ProgramStageInstanceService.delete*(..) )" method="intercept" />
      <aop:before pointcut="execution( * org.hisp.dhis.program.ProgramStageDataElementService.delete*(..) )" method="intercept" />
      <aop:before pointcut="execution( * org.hisp.dhis.program.ProgramIndicatorService.delete*(..) )" method="intercept" />
      <aop:before pointcut="execution( * org.hisp.dhis.trackedentitydatavalue.TrackedEntityDataValueService.delete*(..) )"
        method="intercept" />
      <aop:before pointcut="execution( * org.hisp.dhis.eventchart.EventChartService.delete*(..) )" method="intercept" />
      <aop:before pointcut="execution( * org.hisp.dhis.eventreport.EventReportService.delete*(..) )" method="intercept" />
      <aop:before
        pointcut="execution( * org.hisp.dhis.fileresource.FileResourceService.deleteFileResource( org.hisp.dhis.fileresource.FileResource ) )"
        method="intercept" />
    </aop:aspect>
  </aop:config>

  <!-- Security import -->
  <import resource="security.xml" />
</beans>
