<?xml version="1.0"?>
<!DOCTYPE hibernate-mapping PUBLIC
  "-//Hibernate/Hibernate Mapping DTD 3.0//EN"
  "http://www.hibernate.org/dtd/hibernate-mapping-3.0.dtd"
  [<!ENTITY identifiableProperties SYSTEM "classpath://org/hisp/dhis/common/identifiableProperties.hbm">]
  >

<hibernate-mapping>
  <class name="org.hisp.dhis.legend.LegendSet" table="maplegendset">

    <cache usage="read-write" />

    <id name="id" column="maplegendsetid">
      <generator class="native" />
    </id>
    &identifiableProperties;

    <property name="name" column="name" not-null="true" unique="true" length="230" />

    <property name="symbolizer" column="symbolizer" />

    <set name="legends" cascade="all-delete-orphan">
      <cache usage="read-write" />
      <key column="maplegendsetid" />
      <one-to-many class="org.hisp.dhis.legend.Legend" />
    </set>

    <!-- Dynamic attribute values -->
    <property name="attributeValues" type="jsbAttributeValues"/>

    <property name="translations" type="jblTranslations"/>

    <many-to-one name="createdBy" class="org.hisp.dhis.user.User" column="userid" foreign-key="fk_legendset_userid" />


    <!-- Sharing -->
    <property name="sharing" type="jsbObjectSharing"/>

  </class>

</hibernate-mapping>
